{"abandonar": {"1s": "abandonara", "2s": "abandonaras", "3s": "abandonara", "1p": "abandonáramos", "2p": "abandonarais", "3p": "abandonaran"}, "abordar": {"1s": "abordara", "2s": "abordaras", "3s": "abordara", "1p": "abordáramos", "2p": "abordarais", "3p": "abordaran"}, "abortar": {"1s": "abortara", "2s": "abortaras", "3s": "abortara", "1p": "abortáramos", "2p": "abortarais", "3p": "abortaran"}, "abrazar": {"1s": "abrazara", "2s": "abrazaras", "3s": "abrazara", "1p": "abrazáramos", "2p": "abrazarais", "3p": "abrazaran"}, "abrir": {"1s": "abriera", "2s": "abrieras", "3s": "abriera", "1p": "abriéramos", "2p": "abrierais", "3p": "abrieran"}, "aburrir": {"1s": "aburriera", "2s": "aburrieras", "3s": "aburriera", "1p": "aburriéramos", "2p": "aburrierais", "3p": "aburrieran"}, "aburrirse": {"1s": "me aburriera", "2s": "te aburrieras", "3s": "se aburriera", "1p": "nos aburriéramos", "2p": "os aburrierais", "3p": "se aburrieran"}, "abusar": {"1s": "abusara", "2s": "abusaras", "3s": "abusara", "1p": "abusáramos", "2p": "abusarais", "3p": "abusaran"}, "acabar": {"1s": "acabara", "2s": "acabaras", "3s": "acabara", "1p": "acabáramos", "2p": "acabarais", "3p": "acabaran"}, "acampar": {"1s": "acampara", "2s": "acamparas", "3s": "acampara", "1p": "acampáramos", "2p": "acamparais", "3p": "acamparan"}, "aceptar": {"1s": "aceptara", "2s": "aceptaras", "3s": "aceptara", "1p": "aceptáramos", "2p": "aceptarais", "3p": "aceptaran"}, "acercar": {"1s": "acercara", "2s": "acercaras", "3s": "acercara", "1p": "acercáramos", "2p": "acercarais", "3p": "acercaran"}, "acercarse": {"1s": "me acercara", "2s": "te acercaras", "3s": "se acercara", "1p": "nos acercáramos", "2p": "os acercarais", "3p": "se acercaran"}, "acompañar": {"1s": "acompañara", "2s": "acompañaras", "3s": "acompañara", "1p": "acompañáramos", "2p": "acompañarais", "3p": "acompañaran"}, "aconsejar": {"1s": "aconsejara", "2s": "aconsejaras", "3s": "aconsejara", "1p": "aconsejáramos", "2p": "aconsejarais", "3p": "aconsejaran"}, "acontecer": {"1s": "aconteciera", "2s": "acontecieras", "3s": "aconteciera", "1p": "aconteciéramos", "2p": "acontecierais", "3p": "acontecieran"}, "acordar": {"1s": "acordara", "2s": "acordaras", "3s": "acordara", "1p": "acordáramos", "2p": "acordarais", "3p": "acordaran"}, "acordarse": {"1s": "me acordara", "2s": "te acordaras", "3s": "se acordara", "1p": "nos acordáramos", "2p": "os acordarais", "3p": "se acordaran"}, "acortar": {"1s": "acortara", "2s": "acortaras", "3s": "acortara", "1p": "acortáramos", "2p": "acortarais", "3p": "acortaran"}, "acostar": {"1s": "acostara", "2s": "acostaras", "3s": "acostara", "1p": "acostáramos", "2p": "acostarais", "3p": "acostaran"}, "acostarse": {"1s": "me acostara", "2s": "te acostaras", "3s": "se acostara", "1p": "nos acostáramos", "2p": "os acostarais", "3p": "se acostaran"}, "acostumbrar": {"1s": "acostumbrara", "2s": "acostumbraras", "3s": "acostumbrara", "1p": "acostumbráramos", "2p": "acostumbrarais", "3p": "acostumbraran"}, "acostumbrarse": {"1s": "me acostumbrara", "2s": "te acostumbraras", "3s": "se acostumbrara", "1p": "nos acostumbráramos", "2p": "os acostumbrarais", "3p": "se acostumbraran"}, "actuar": {"1s": "actuara", "2s": "actuaras", "3s": "actuara", "1p": "actuáramos", "2p": "actuarais", "3p": "actuaran"}, "adivinar": {"1s": "adivinara", "2s": "adivinaras", "3s": "adivinara", "1p": "adivináramos", "2p": "adivinarais", "3p": "adivinaran"}, "admirar": {"1s": "admirara", "2s": "admiraras", "3s": "admirara", "1p": "admiráramos", "2p": "admirarais", "3p": "admiraran"}, "admitir": {"1s": "admitiera", "2s": "admitieras", "3s": "admitiera", "1p": "admitiéramos", "2p": "admitierais", "3p": "admitieran"}, "adorar": {"1s": "adorara", "2s": "adoraras", "3s": "adorara", "1p": "adoráramos", "2p": "adorarais", "3p": "adoraran"}, "adornar": {"1s": "adornara", "2s": "adornaras", "3s": "adornara", "1p": "adornáramos", "2p": "adornarais", "3p": "adornaran"}, "advertir": {"1s": "advirtiera", "2s": "advirtieras", "3s": "advirtiera", "1p": "advirtiéramos", "2p": "advirtierais", "3p": "advirtieran"}, "afeitar": {"1s": "afeitara", "2s": "afeitaras", "3s": "afeitara", "1p": "afeitáramos", "2p": "afeitarais", "3p": "afeitaran"}, "afeitarse": {"1s": "me afeitara", "2s": "te afeitaras", "3s": "se afeitara", "1p": "nos afeitáramos", "2p": "os afeitarais", "3p": "se afeitaran"}, "afirmar": {"1s": "afirmara", "2s": "afirmaras", "3s": "afirmara", "1p": "afirmáramos", "2p": "afirmarais", "3p": "afirmaran"}, "afligir": {"1s": "afligiera", "2s": "afligieras", "3s": "afligiera", "1p": "afligiéramos", "2p": "afligierais", "3p": "afligieran"}, "agorar": {"1s": "agorara", "2s": "agoraras", "3s": "agorara", "1p": "agoráramos", "2p": "agorarais", "3p": "agoraran"}, "agradar": {"1s": "agradara", "2s": "agradaras", "3s": "agradara", "1p": "agradáramos", "2p": "agradarais", "3p": "agradaran"}, "agradecer": {"1s": "agradeciera", "2s": "agradecieras", "3s": "agradeciera", "1p": "agradeciéramos", "2p": "agradecierais", "3p": "agradecieran"}, "aguantar": {"1s": "aguantara", "2s": "aguantaras", "3s": "aguantara", "1p": "aguantáramos", "2p": "aguantarais", "3p": "aguantaran"}, "ahorcar": {"1s": "ahorcara", "2s": "ahorcaras", "3s": "ahorcara", "1p": "ahorcáramos", "2p": "ahorcarais", "3p": "ahorcaran"}, "ahorrar": {"1s": "ahorrara", "2s": "ahorraras", "3s": "ahorrara", "1p": "ahorráramos", "2p": "ahorrarais", "3p": "ahorraran"}, "alcanzar": {"1s": "alcanzara", "2s": "alcanzaras", "3s": "alcanzara", "1p": "alcanzáramos", "2p": "alcanzarais", "3p": "alcanzaran"}, "alegrar": {"1s": "alegrara", "2s": "alegraras", "3s": "alegrara", "1p": "alegráramos", "2p": "alegrarais", "3p": "alegraran"}, "alegrarse": {"1s": "me alegrara", "2s": "te alegraras", "3s": "se alegrara", "1p": "nos alegráramos", "2p": "os alegrarais", "3p": "se alegraran"}, "alentar": {"1s": "alentara", "2s": "alentaras", "3s": "alentara", "1p": "alentáramos", "2p": "alentarais", "3p": "alentaran"}, "aliviar": {"1s": "aliviara", "2s": "aliviaras", "3s": "aliviara", "1p": "aliviáramos", "2p": "aliviarais", "3p": "aliviaran"}, "almorzar": {"1s": "almorzara", "2s": "almorzaras", "3s": "almorzara", "1p": "almorzáramos", "2p": "almorzarais", "3p": "almorzaran"}, "alquilar": {"1s": "alquilara", "2s": "alquilaras", "3s": "alquilara", "1p": "alquiláramos", "2p": "alquilarais", "3p": "alquilaran"}, "amanecer": {"1s": "amaneciera", "2s": "amanecieras", "3s": "amaneciera", "1p": "amaneciéramos", "2p": "amanecierais", "3p": "amanecieran"}, "amar": {"1s": "amara", "2s": "amaras", "3s": "amara", "1p": "amáramos", "2p": "amarais", "3p": "amaran"}, "amenazar": {"1s": "amenazara", "2s": "amenazaras", "3s": "amenazara", "1p": "amenazáramos", "2p": "amenazarais", "3p": "amenazaran"}, "andar": {"1s": "anduviera", "2s": "anduvieras", "3s": "anduviera", "1p": "anduviéramos", "2p": "anduvierais", "3p": "anduvieran"}, "anhelar": {"1s": "anhelara", "2s": "anhelaras", "3s": "anhelara", "1p": "anheláramos", "2p": "anhelarais", "3p": "anhelaran"}, "anunciar": {"1s": "anunciara", "2s": "anunciaras", "3s": "anunciara", "1p": "anunciáramos", "2p": "anunciarais", "3p": "anunciaran"}, "añadir": {"1s": "añadiera", "2s": "añadieras", "3s": "añadiera", "1p": "añadiéramos", "2p": "añadierais", "3p": "añadieran"}, "apoyar": {"1s": "apoyara", "2s": "apoyaras", "3s": "apoyara", "1p": "apoyáramos", "2p": "apoyarais", "3p": "apoyaran"}, "apagar": {"1s": "apagara", "2s": "apagaras", "3s": "apagara", "1p": "apagáramos", "2p": "apagarais", "3p": "apagaran"}, "aparecer": {"1s": "apareciera", "2s": "aparecieras", "3s": "apareciera", "1p": "apareciéramos", "2p": "aparecierais", "3p": "aparecieran"}, "aplaudir": {"1s": "aplaudiera", "2s": "aplaudieras", "3s": "aplaudiera", "1p": "aplaudiéramos", "2p": "aplaudierais", "3p": "aplaudieran"}, "aplicar": {"1s": "aplicara", "2s": "aplicaras", "3s": "aplicara", "1p": "aplicáramos", "2p": "aplicarais", "3p": "aplicaran"}, "apostar": {"1s": "apostara", "2s": "apostaras", "3s": "apostara", "1p": "apostáramos", "2p": "apostarais", "3p": "apostaran"}, "apreciar": {"1s": "apreciara", "2s": "apreciaras", "3s": "apreciara", "1p": "apreciáramos", "2p": "apreciarais", "3p": "apreciaran"}, "aprender": {"1s": "aprendiera", "2s": "aprendieras", "3s": "aprendiera", "1p": "aprendiéramos", "2p": "aprendierais", "3p": "aprendieran"}, "apretar": {"1s": "apretara", "2s": "apretaras", "3s": "apretara", "1p": "apretáramos", "2p": "apretarais", "3p": "apretaran"}, "aprobar": {"1s": "aprobara", "2s": "aprobaras", "3s": "aprobara", "1p": "aprobáramos", "2p": "aprobarais", "3p": "aprobaran"}, "arreglar": {"1s": "arreglara", "2s": "arreglaras", "3s": "arreglara", "1p": "arregláramos", "2p": "arreglarais", "3p": "arreglaran"}, "arrepentirse": {"1s": "me arrepintiera", "2s": "te arrepintieras", "3s": "se arrepintiera", "1p": "nos arrepintiéramos", "2p": "os arrepintierais", "3p": "se arrepintieran"}, "arrojar": {"1s": "arrojara", "2s": "arrojaras", "3s": "arrojara", "1p": "arrojáramos", "2p": "arrojarais", "3p": "arrojaran"}, "asistir": {"1s": "asistiera", "2s": "asistieras", "3s": "asistiera", "1p": "asistiéramos", "2p": "asistierais", "3p": "asistieran"}, "asociar": {"1s": "asociara", "2s": "asociaras", "3s": "asociara", "1p": "asociáramos", "2p": "asociarais", "3p": "asociaran"}, "aspirar": {"1s": "aspirara", "2s": "aspiraras", "3s": "aspirara", "1p": "aspiráramos", "2p": "aspirarais", "3p": "aspiraran"}, "asustar": {"1s": "asustara", "2s": "asustaras", "3s": "asustara", "1p": "asustáramos", "2p": "asustarais", "3p": "asustaran"}, "asustarse": {"1s": "me asustara", "2s": "te asustaras", "3s": "se asustara", "1p": "nos asustáramos", "2p": "os asustarais", "3p": "se asustaran"}, "atacar": {"1s": "atacara", "2s": "atacaras", "3s": "atacara", "1p": "atacáramos", "2p": "atacarais", "3p": "atacaran"}, "atender": {"1s": "atendiera", "2s": "atendieras", "3s": "atendiera", "1p": "atendiéramos", "2p": "atendierais", "3p": "atendieran"}, "atraer": {"1s": "atrajera", "2s": "atrajeras", "3s": "atrajera", "1p": "atrajéramos", "2p": "atrajerais", "3p": "atrajeran"}, "atravesar": {"1s": "atravesara", "2s": "atravesaras", "3s": "atravesara", "1p": "atravesáramos", "2p": "atravesarais", "3p": "atravesaran"}, "atreverse": {"1s": "me atreviera", "2s": "te atrevieras", "3s": "se atreviera", "1p": "nos atreviéramos", "2p": "os atrevierais", "3p": "se atrevieran"}, "aumentar": {"1s": "aumentara", "2s": "aumentaras", "3s": "aumentara", "1p": "aumentáramos", "2p": "aumentarais", "3p": "aumentaran"}, "avanzar": {"1s": "avanzara", "2s": "avanzaras", "3s": "avanzara", "1p": "avanzáramos", "2p": "avanzarais", "3p": "avanzaran"}, "averiguar": {"1s": "averiguara", "2s": "averiguaras", "3s": "averiguara", "1p": "averiguáramos", "2p": "averiguarais", "3p": "averiguaran"}, "avisar": {"1s": "avisara", "2s": "avisaras", "3s": "avisara", "1p": "avisáramos", "2p": "avisarais", "3p": "avisaran"}, "ayudar": {"1s": "ayudara", "2s": "ayudaras", "3s": "ayudara", "1p": "ayudáramos", "2p": "ayudarais", "3p": "ayudaran"}, "bajar": {"1s": "bajara", "2s": "bajaras", "3s": "bajara", "1p": "bajáramos", "2p": "bajarais", "3p": "bajaran"}, "bañar": {"1s": "bañara", "2s": "bañaras", "3s": "bañara", "1p": "bañáramos", "2p": "bañarais", "3p": "bañaran"}, "bañarse": {"1s": "me bañara", "2s": "te bañaras", "3s": "se bañara", "1p": "nos bañáramos", "2p": "os bañarais", "3p": "se bañaran"}, "barrer": {"1s": "barriera", "2s": "barrieras", "3s": "barriera", "1p": "barriéramos", "2p": "barrierais", "3p": "barrieran"}, "batir": {"1s": "batiera", "2s": "batieras", "3s": "batiera", "1p": "batiéramos", "2p": "batierais", "3p": "batieran"}, "bautizar": {"1s": "bautizara", "2s": "bautizaras", "3s": "bautizara", "1p": "bautizáramos", "2p": "bautizarais", "3p": "bautizaran"}, "beber": {"1s": "bebiera", "2s": "bebieras", "3s": "bebiera", "1p": "bebiéramos", "2p": "bebierais", "3p": "bebieran"}, "bendecir": {"1s": "bendijera", "2s": "bendijeras", "3s": "bendijera", "1p": "bendijéramos", "2p": "bendijerais", "3p": "bendijeran"}, "bordar": {"1s": "bordara", "2s": "bordaras", "3s": "bordara", "1p": "bordáramos", "2p": "bordarais", "3p": "bordaran"}, "borrar": {"1s": "borrara", "2s": "borraras", "3s": "borrara", "1p": "borráramos", "2p": "borrarais", "3p": "borraran"}, "brillar": {"1s": "brillara", "2s": "brillaras", "3s": "brillara", "1p": "brilláramos", "2p": "brillarais", "3p": "brillaran"}, "brindar": {"1s": "brindara", "2s": "brindaras", "3s": "brindara", "1p": "brindáramos", "2p": "brindarais", "3p": "brindaran"}, "broncearse": {"1s": "me bronceara", "2s": "te broncearas", "3s": "se bronceara", "1p": "nos bronceáramos", "2p": "os broncearais", "3p": "se broncearan"}, "bucear": {"1s": "buceara", "2s": "bucearas", "3s": "buceara", "1p": "buceáramos", "2p": "bucearais", "3p": "bucearan"}, "burlar": {"1s": "burlara", "2s": "burlaras", "3s": "burlara", "1p": "burláramos", "2p": "burlarais", "3p": "burlaran"}, "burlarse": {"1s": "me burlara", "2s": "te burlaras", "3s": "se burlara", "1p": "nos burláramos", "2p": "os burlarais", "3p": "se burlaran"}, "buscar": {"1s": "buscara", "2s": "buscaras", "3s": "buscara", "1p": "buscáramos", "2p": "buscarais", "3p": "buscaran"}, "caber": {"1s": "cupiera", "2s": "cupieras", "3s": "cupiera", "1p": "cupiéramos", "2p": "cupierais", "3p": "cupieran"}, "caer": {"1s": "cayera", "2s": "cayeras", "3s": "cayera", "1p": "cayéramos", "2p": "cayerais", "3p": "cayeran"}, "calcular": {"1s": "calculara", "2s": "calcularas", "3s": "calculara", "1p": "calculáramos", "2p": "calcularais", "3p": "calcularan"}, "calentar": {"1s": "calentara", "2s": "calentaras", "3s": "calentara", "1p": "calentáramos", "2p": "calentarais", "3p": "calentaran"}, "calentarse": {"1s": "me calentara", "2s": "te calentaras", "3s": "se calentara", "1p": "nos calentáramos", "2p": "os calentarais", "3p": "se calentaran"}, "callar": {"1s": "callara", "2s": "callaras", "3s": "callara", "1p": "calláramos", "2p": "callarais", "3p": "callaran"}, "callarse": {"1s": "me callara", "2s": "te callaras", "3s": "se callara", "1p": "nos calláramos", "2p": "os callarais", "3p": "se callaran"}, "calmar": {"1s": "calmara", "2s": "calmaras", "3s": "calmara", "1p": "calmáramos", "2p": "calmarais", "3p": "calmaran"}, "calmarse": {"1s": "me calmara", "2s": "te calmaras", "3s": "se calmara", "1p": "nos calmáramos", "2p": "os calmarais", "3p": "se calmaran"}, "caminar": {"1s": "caminara", "2s": "caminaras", "3s": "caminara", "1p": "camináramos", "2p": "caminarais", "3p": "caminaran"}, "cancelar": {"1s": "cancelara", "2s": "cancelaras", "3s": "cancelara", "1p": "canceláramos", "2p": "cancelarais", "3p": "cancelaran"}, "cansar": {"1s": "cansara", "2s": "cansaras", "3s": "cansara", "1p": "cansáramos", "2p": "cansarais", "3p": "cansaran"}, "cansarse": {"1s": "me cansara", "2s": "te cansaras", "3s": "se cansara", "1p": "nos cansáramos", "2p": "os cansarais", "3p": "se cansaran"}, "caracterizar": {"1s": "caracterizara", "2s": "caracterizaras", "3s": "caracterizara", "1p": "caracterizáramos", "2p": "caracterizarais", "3p": "caracterizaran"}, "cargar": {"1s": "cargara", "2s": "cargaras", "3s": "cargara", "1p": "cargáramos", "2p": "cargarais", "3p": "cargaran"}, "casar": {"1s": "casara", "2s": "casaras", "3s": "casara", "1p": "casáramos", "2p": "casarais", "3p": "casaran"}, "casarse": {"1s": "me casara", "2s": "te casaras", "3s": "se casara", "1p": "nos casáramos", "2p": "os casarais", "3p": "se casaran"}, "castigar": {"1s": "castigara", "2s": "castigaras", "3s": "castigara", "1p": "castigáramos", "2p": "castigarais", "3p": "castigaran"}, "causar": {"1s": "causara", "2s": "causaras", "3s": "causara", "1p": "causáramos", "2p": "causarais", "3p": "causaran"}, "cazar": {"1s": "cazara", "2s": "cazaras", "3s": "cazara", "1p": "cazáramos", "2p": "cazarais", "3p": "cazaran"}, "celebrar": {"1s": "celebrara", "2s": "celebraras", "3s": "celebrara", "1p": "celebráramos", "2p": "celebrarais", "3p": "celebraran"}, "cenar": {"1s": "cenara", "2s": "cenaras", "3s": "cenara", "1p": "cenáramos", "2p": "cenarais", "3p": "cenaran"}, "censurar": {"1s": "censurara", "2s": "censuraras", "3s": "censurara", "1p": "censuráramos", "2p": "censurarais", "3p": "censuraran"}, "cepillar": {"1s": "cepillara", "2s": "cepillaras", "3s": "cepillara", "1p": "cepilláramos", "2p": "cepillarais", "3p": "cepillaran"}, "cerrar": {"1s": "cerrara", "2s": "cerraras", "3s": "cerrara", "1p": "cerráramos", "2p": "cerrarais", "3p": "cerraran"}, "cesar": {"1s": "cesara", "2s": "cesaras", "3s": "cesara", "1p": "cesáramos", "2p": "cesarais", "3p": "cesaran"}, "charlar": {"1s": "charlara", "2s": "charlaras", "3s": "charlara", "1p": "charláramos", "2p": "charlarais", "3p": "charlaran"}, "chismear": {"1s": "chismeara", "2s": "chismearas", "3s": "chismeara", "1p": "chismeáramos", "2p": "chismearais", "3p": "chismearan"}, "chocar": {"1s": "chocara", "2s": "chocaras", "3s": "chocara", "1p": "chocáramos", "2p": "chocarais", "3p": "chocaran"}, "civilizar": {"1s": "civilizara", "2s": "civilizaras", "3s": "civilizara", "1p": "civilizáramos", "2p": "civilizarais", "3p": "civilizaran"}, "clarificar": {"1s": "clarificara", "2s": "clarificaras", "3s": "clarificara", "1p": "clarificáramos", "2p": "clarificarais", "3p": "clarificaran"}, "clasificar": {"1s": "clasificara", "2s": "clasificaras", "3s": "clasificara", "1p": "clasificáramos", "2p": "clasificarais", "3p": "clasificaran"}, "cobrar": {"1s": "cobrara", "2s": "cobraras", "3s": "cobrara", "1p": "cobráramos", "2p": "cobrarais", "3p": "cobraran"}, "cocinar": {"1s": "cocinara", "2s": "cocinaras", "3s": "cocinara", "1p": "cocináramos", "2p": "cocinarais", "3p": "cocinaran"}, "coger": {"1s": "cogiera", "2s": "cogieras", "3s": "cogiera", "1p": "cogiéramos", "2p": "cogierais", "3p": "cogieran"}, "colgar": {"1s": "colgara", "2s": "colgaras", "3s": "colgara", "1p": "colgáramos", "2p": "colgarais", "3p": "colgaran"}, "colocar": {"1s": "colocara", "2s": "colocaras", "3s": "colocara", "1p": "colocáramos", "2p": "colocarais", "3p": "colocaran"}, "colonizar": {"1s": "colonizara", "2s": "colonizaras", "3s": "colonizara", "1p": "colonizáramos", "2p": "colonizarais", "3p": "colonizaran"}, "combatir": {"1s": "combatiera", "2s": "combatieras", "3s": "combatiera", "1p": "combatiéramos", "2p": "combatierais", "3p": "combatieran"}, "comenzar": {"1s": "comenzara", "2s": "comenzaras", "3s": "comenzara", "1p": "comenzáramos", "2p": "comenzarais", "3p": "comenzaran"}, "comer": {"1s": "comiera", "2s": "comieras", "3s": "comiera", "1p": "comiéramos", "2p": "comierais", "3p": "comieran"}, "competir": {"1s": "compitiera", "2s": "compitieras", "3s": "compitiera", "1p": "compitiéramos", "2p": "compitierais", "3p": "compitieran"}, "componer": {"1s": "compusiera", "2s": "compusieras", "3s": "compusiera", "1p": "compusiéramos", "2p": "compusierais", "3p": "compusieran"}, "comprar": {"1s": "comprara", "2s": "compraras", "3s": "comprara", "1p": "compráramos", "2p": "comprarais", "3p": "compraran"}, "comprender": {"1s": "comprendiera", "2s": "comprendieras", "3s": "comprendiera", "1p": "comprendiéramos", "2p": "comprendierais", "3p": "comprendieran"}, "comunicar": {"1s": "comunicara", "2s": "comunicaras", "3s": "comunicara", "1p": "comunicáramos", "2p": "comunicarais", "3p": "comunicaran"}, "comunicarse": {"1s": "me comunicara", "2s": "te comunicaras", "3s": "se comunicara", "1p": "nos comunicáramos", "2p": "os comunicarais", "3p": "se comunicaran"}, "condenar": {"1s": "condenara", "2s": "condenaras", "3s": "condenara", "1p": "condenáramos", "2p": "condenarais", "3p": "condenaran"}, "conducir": {"1s": "condujera", "2s": "condujeras", "3s": "condujera", "1p": "condujéramos", "2p": "condujerais", "3p": "condujeran"}, "confesar": {"1s": "confesara", "2s": "confesaras", "3s": "confesara", "1p": "confesáramos", "2p": "confesarais", "3p": "confesaran"}, "confiar": {"1s": "confiara", "2s": "confiaras", "3s": "confiara", "1p": "confiáramos", "2p": "confiarais", "3p": "confiaran"}, "confirmar": {"1s": "confirmara", "2s": "confirmaras", "3s": "confirmara", "1p": "confirmáramos", "2p": "confirmarais", "3p": "confirmaran"}, "compartir": {"1s": "compartiera", "2s": "compartieras", "3s": "compartiera", "1p": "compartiéramos", "2p": "compartierais", "3p": "compartieran"}, "confiscar": {"1s": "confiscara", "2s": "confiscaras", "3s": "confiscara", "1p": "confiscáramos", "2p": "confiscarais", "3p": "confiscaran"}, "conjugar": {"1s": "conjugara", "2s": "conjugaras", "3s": "conjugara", "1p": "conjugáramos", "2p": "conjugarais", "3p": "conjugaran"}, "conocer": {"1s": "conociera", "2s": "conocieras", "3s": "conociera", "1p": "conociéramos", "2p": "conocierais", "3p": "conocieran"}, "conquistar": {"1s": "conquistara", "2s": "conquistaras", "3s": "conquistara", "1p": "conquistáramos", "2p": "conquistarais", "3p": "conquistaran"}, "conseguir": {"1s": "consiguiera", "2s": "consiguieras", "3s": "consiguiera", "1p": "consiguiéramos", "2p": "consiguierais", "3p": "consiguieran"}, "consentir": {"1s": "consintiera", "2s": "consintieras", "3s": "consintiera", "1p": "consintiéramos", "2p": "consintierais", "3p": "consintieran"}, "conservar": {"1s": "conservara", "2s": "conservaras", "3s": "conservara", "1p": "conserváramos", "2p": "conservarais", "3p": "conservaran"}, "consistir": {"1s": "consistiera", "2s": "consistieras", "3s": "consistiera", "1p": "consistiéramos", "2p": "consistierais", "3p": "consistieran"}, "constituir": {"1s": "constituyera", "2s": "constituyeras", "3s": "constituyera", "1p": "constituyéramos", "2p": "constituyerais", "3p": "constituyeran"}, "construir": {"1s": "construyera", "2s": "construyeras", "3s": "construyera", "1p": "construyéramos", "2p": "construyerais", "3p": "construyeran"}, "consumir": {"1s": "consumiera", "2s": "consumieras", "3s": "consumiera", "1p": "consumiéramos", "2p": "consumierais", "3p": "consumieran"}, "contaminar": {"1s": "contaminara", "2s": "contaminaras", "3s": "contaminara", "1p": "contamináramos", "2p": "contaminarais", "3p": "contaminaran"}, "contar": {"1s": "contara", "2s": "contaras", "3s": "contara", "1p": "contáramos", "2p": "contarais", "3p": "contaran"}, "contener": {"1s": "contuviera", "2s": "contuvieras", "3s": "contuviera", "1p": "contuviéramos", "2p": "contuvierais", "3p": "contuvieran"}, "contestar": {"1s": "contestara", "2s": "contestaras", "3s": "contestara", "1p": "contestáramos", "2p": "contestarais", "3p": "contestaran"}, "continuar": {"1s": "continuara", "2s": "continuaras", "3s": "continuara", "1p": "continuáramos", "2p": "continuarais", "3p": "continuaran"}, "contribuir": {"1s": "contribuyera", "2s": "contribuyeras", "3s": "contribuyera", "1p": "contribuyéramos", "2p": "contribuyerais", "3p": "contribuyeran"}, "controlar": {"1s": "controlara", "2s": "controlaras", "3s": "controlara", "1p": "controláramos", "2p": "controlarais", "3p": "controlaran"}, "convencer": {"1s": "convenciera", "2s": "convencieras", "3s": "convenciera", "1p": "convenciéramos", "2p": "convencierais", "3p": "convencieran"}, "convenir": {"1s": "conviniera", "2s": "convinieras", "3s": "conviniera", "1p": "conviniéramos", "2p": "convinierais", "3p": "convinieran"}, "conversar": {"1s": "conversara", "2s": "conversaras", "3s": "conversara", "1p": "conversáramos", "2p": "conversarais", "3p": "conversaran"}, "convertir": {"1s": "convirtiera", "2s": "convirtieras", "3s": "convirtiera", "1p": "convirtiéramos", "2p": "convirtierais", "3p": "convirtieran"}, "convidar": {"1s": "convidara", "2s": "convidaras", "3s": "convidara", "1p": "convidáramos", "2p": "convidarais", "3p": "convidaran"}, "copiar": {"1s": "copiara", "2s": "copiaras", "3s": "copiara", "1p": "copiáramos", "2p": "copiarais", "3p": "copiaran"}, "cortar": {"1s": "cortara", "2s": "cortaras", "3s": "cortara", "1p": "cortáramos", "2p": "cortarais", "3p": "cortaran"}, "corregir": {"1s": "corrigiera", "2s": "corrigieras", "3s": "corrigiera", "1p": "corrigiéramos", "2p": "corrigierais", "3p": "corrigieran"}, "correr": {"1s": "corriera", "2s": "corrieras", "3s": "corriera", "1p": "corriéramos", "2p": "corrierais", "3p": "corrieran"}, "coser": {"1s": "cosiera", "2s": "cosieras", "3s": "cosiera", "1p": "cosiéramos", "2p": "cosierais", "3p": "cosieran"}, "costar": {"1s": "costara", "2s": "costaras", "3s": "costara", "1p": "costáramos", "2p": "costarais", "3p": "costaran"}, "crear": {"1s": "creara", "2s": "crearas", "3s": "creara", "1p": "creáramos", "2p": "crearais", "3p": "crearan"}, "crecer": {"1s": "creciera", "2s": "crecieras", "3s": "creciera", "1p": "creciéramos", "2p": "crecierais", "3p": "crecieran"}, "creer": {"1s": "creyera", "2s": "creyeras", "3s": "creyera", "1p": "creyéramos", "2p": "creyerais", "3p": "creyeran"}, "criar": {"1s": "criara", "2s": "criaras", "3s": "criara", "1p": "criáramos", "2p": "criarais", "3p": "criaran"}, "criarse": {"1s": "me criara", "2s": "te criaras", "3s": "se criara", "1p": "nos criáramos", "2p": "os criarais", "3p": "se criaran"}, "criticar": {"1s": "criticara", "2s": "criticaras", "3s": "criticara", "1p": "criticáramos", "2p": "criticarais", "3p": "criticaran"}, "crucificar": {"1s": "crucificara", "2s": "crucificaras", "3s": "crucificara", "1p": "crucificáramos", "2p": "crucificarais", "3p": "crucificaran"}, "cruzar": {"1s": "cruzara", "2s": "cruzaras", "3s": "cruzara", "1p": "cruzáramos", "2p": "cruzarais", "3p": "cruzaran"}, "cubrir": {"1s": "cubriera", "2s": "cubrieras", "3s": "cubriera", "1p": "cubriéramos", "2p": "cubrierais", "3p": "cubrieran"}, "cuidar": {"1s": "cuidara", "2s": "cuidaras", "3s": "cuidara", "1p": "cuidáramos", "2p": "cuidarais", "3p": "cuidaran"}, "culpar": {"1s": "culpara", "2s": "culparas", "3s": "culpara", "1p": "culpáramos", "2p": "culparais", "3p": "culparan"}, "cultivar": {"1s": "cultivara", "2s": "cultivaras", "3s": "cultivara", "1p": "cultiváramos", "2p": "cultivarais", "3p": "cultivaran"}, "cumplir": {"1s": "cumpliera", "2s": "cumplieras", "3s": "cumpliera", "1p": "cumpliéramos", "2p": "cumplierais", "3p": "cumplieran"}, "curar": {"1s": "curara", "2s": "curaras", "3s": "curara", "1p": "curáramos", "2p": "curarais", "3p": "curaran"}, "dar": {"1s": "diera", "2s": "dieras", "3s": "diera", "1p": "diéramos", "2p": "dierais", "3p": "dieran"}, "deber": {"1s": "debiera", "2s": "debieras", "3s": "debiera", "1p": "debiéramos", "2p": "debierais", "3p": "debieran"}, "decidir": {"1s": "decidiera", "2s": "decidieras", "3s": "decidiera", "1p": "decidiéramos", "2p": "decidierais", "3p": "decidieran"}, "decidirse": {"1s": "me decidiera", "2s": "te decidieras", "3s": "se decidiera", "1p": "nos decidiéramos", "2p": "os decidierais", "3p": "se decidieran"}, "decir": {"1s": "dijera", "2s": "dijeras", "3s": "dijera", "1p": "dijéramos", "2p": "dijerais", "3p": "dijeran"}, "declarar": {"1s": "declarara", "2s": "declararas", "3s": "declarara", "1p": "declaráramos", "2p": "declararais", "3p": "declararan"}, "decorar": {"1s": "decorara", "2s": "decoraras", "3s": "decorara", "1p": "decoráramos", "2p": "decorarais", "3p": "decoraran"}, "dedicar": {"1s": "dedicara", "2s": "dedicaras", "3s": "dedicara", "1p": "dedicáramos", "2p": "dedicarais", "3p": "dedicaran"}, "dedicarse": {"1s": "me dedicara", "2s": "te dedicaras", "3s": "se dedicara", "1p": "nos dedicáramos", "2p": "os dedicarais", "3p": "se dedicaran"}, "defender": {"1s": "defendiera", "2s": "defendieras", "3s": "defendiera", "1p": "defendiéramos", "2p": "defendierais", "3p": "defendieran"}, "dejar": {"1s": "dejara", "2s": "dejaras", "3s": "dejara", "1p": "dejáramos", "2p": "dejarais", "3p": "dejaran"}, "demostrar": {"1s": "demostrara", "2s": "demostraras", "3s": "demostrara", "1p": "demostráramos", "2p": "demostrarais", "3p": "demostraran"}, "depender": {"1s": "dependiera", "2s": "dependieras", "3s": "dependiera", "1p": "dependiéramos", "2p": "dependierais", "3p": "dependieran"}, "depositar": {"1s": "depositara", "2s": "depositaras", "3s": "depositara", "1p": "depositáramos", "2p": "depositarais", "3p": "depositaran"}, "deprimir": {"1s": "deprimiera", "2s": "deprimieras", "3s": "deprimiera", "1p": "deprimiéramos", "2p": "deprimierais", "3p": "deprimieran"}, "derretir": {"1s": "derritiera", "2s": "derritieras", "3s": "derritiera", "1p": "derritiéramos", "2p": "derritierais", "3p": "derritieran"}, "desagradar": {"1s": "desagradara", "2s": "desagradaras", "3s": "desagradara", "1p": "desagradáramos", "2p": "desagradarais", "3p": "desagradaran"}, "desagradecer": {"1s": "desagradeciera", "2s": "desagradecieras", "3s": "desagradeciera", "1p": "desagradeciéramos", "2p": "desagradecierais", "3p": "desagradecieran"}, "desaparecer": {"1s": "desapareciera", "2s": "desaparecieras", "3s": "desapareciera", "1p": "desapareciéramos", "2p": "desaparecierais", "3p": "desaparecieran"}, "desayunar": {"1s": "desayunara", "2s": "desayunaras", "3s": "desayunara", "1p": "desayunáramos", "2p": "desayunarais", "3p": "desayunaran"}, "descansar": {"1s": "descansara", "2s": "descansaras", "3s": "descansara", "1p": "descansáramos", "2p": "descansarais", "3p": "descansaran"}, "descender": {"1s": "descendiera", "2s": "descendieras", "3s": "descendiera", "1p": "descendiéramos", "2p": "descendierais", "3p": "descendieran"}, "describir": {"1s": "describiera", "2s": "describieras", "3s": "describiera", "1p": "describiéramos", "2p": "describierais", "3p": "describieran"}, "descubrir": {"1s": "descubriera", "2s": "descubrieras", "3s": "descubriera", "1p": "descubriéramos", "2p": "descubrierais", "3p": "descubrieran"}, "desarrollar": {"1s": "desarrollara", "2s": "desarrollaras", "3s": "desarrollara", "1p": "desarrolláramos", "2p": "desarrollarais", "3p": "desarrollaran"}, "desarrollarse": {"1s": "me desarrollara", "2s": "te desarrollaras", "3s": "se desarrollara", "1p": "nos desarrolláramos", "2p": "os desarrollarais", "3p": "se desarrollaran"}, "desear": {"1s": "deseara", "2s": "desearas", "3s": "deseara", "1p": "deseáramos", "2p": "desearais", "3p": "desearan"}, "deshacer": {"1s": "deshiciera", "2s": "deshicieras", "3s": "deshiciera", "1p": "deshiciéramos", "2p": "deshicierais", "3p": "deshicieran"}, "despedir": {"1s": "despidiera", "2s": "despidieras", "3s": "despidiera", "1p": "despidiéramos", "2p": "despidierais", "3p": "despidieran"}, "despertar": {"1s": "despertara", "2s": "despertaras", "3s": "despertara", "1p": "despertáramos", "2p": "despertarais", "3p": "despertaran"}, "despertarse": {"1s": "me despertara", "2s": "te despertaras", "3s": "se despertara", "1p": "nos despertáramos", "2p": "os despertarais", "3p": "se despertaran"}, "destruir": {"1s": "destruyera", "2s": "destruyeras", "3s": "destruyera", "1p": "destruyéramos", "2p": "destruyerais", "3p": "destruyeran"}, "detener": {"1s": "detuviera", "2s": "detuvieras", "3s": "detuviera", "1p": "detuviéramos", "2p": "detuvierais", "3p": "detuvieran"}, "detenerse": {"1s": "me detuviera", "2s": "te detuvieras", "3s": "se detuviera", "1p": "nos detuviéramos", "2p": "os detuvierais", "3p": "se detuvieran"}, "detestar": {"1s": "detestara", "2s": "detestaras", "3s": "detestara", "1p": "detestáramos", "2p": "detestarais", "3p": "detestaran"}, "devolver": {"1s": "devolviera", "2s": "devolvieras", "3s": "devolviera", "1p": "devolviéramos", "2p": "devolvierais", "3p": "devolvieran"}, "devorar": {"1s": "devorara", "2s": "devoraras", "3s": "devorara", "1p": "devoráramos", "2p": "devorarais", "3p": "devoraran"}, "dibujar": {"1s": "dibujara", "2s": "dibujaras", "3s": "dibujara", "1p": "dibujáramos", "2p": "dibujarais", "3p": "dibujaran"}, "dirigir": {"1s": "dirigiera", "2s": "dirigieras", "3s": "dirigiera", "1p": "dirigiéramos", "2p": "dirigierais", "3p": "dirigieran"}, "diseñar": {"1s": "diseñara", "2s": "diseñaras", "3s": "diseñara", "1p": "diseñáramos", "2p": "diseñarais", "3p": "diseñaran"}, "doler": {"1s": "", "2s": "", "3s": "doliera", "1p": "", "2p": "", "3p": "dolieran"}, "disfrutar": {"1s": "disfrutara", "2s": "disfrutaras", "3s": "disfrutara", "1p": "disfrutáramos", "2p": "disfrutarais", "3p": "disfrutaran"}, "disgustar": {"1s": "disgustara", "2s": "disgustaras", "3s": "disgustara", "1p": "disgustáramos", "2p": "disgustarais", "3p": "disgustaran"}, "disminuir": {"1s": "disminuyera", "2s": "disminuyeras", "3s": "disminuyera", "1p": "disminuyéramos", "2p": "disminuyerais", "3p": "disminuyeran"}, "distinguir": {"1s": "distinguiera", "2s": "distinguieras", "3s": "distinguiera", "1p": "distinguiéramos", "2p": "distinguierais", "3p": "distinguieran"}, "distribuir": {"1s": "distribuyera", "2s": "distribuyeras", "3s": "distribuyera", "1p": "distribuyéramos", "2p": "distribuyerais", "3p": "distribuyeran"}, "divertir": {"1s": "divirtiera", "2s": "divirtieras", "3s": "divirtiera", "1p": "divirtiéramos", "2p": "divirtierais", "3p": "divirtieran"}, "divertirse": {"1s": "me divirtiera", "2s": "te divirtieras", "3s": "se divirtiera", "1p": "nos divirtiéramos", "2p": "os divirtierais", "3p": "se divirtieran"}, "divorciar": {"1s": "divorciara", "2s": "divorciaras", "3s": "divorciara", "1p": "divorciáramos", "2p": "divorciarais", "3p": "divorciaran"}, "divorciarse": {"1s": "me divorciara", "2s": "te divorciaras", "3s": "se divorciara", "1p": "nos divorciáramos", "2p": "os divorciarais", "3p": "se divorciaran"}, "doblar": {"1s": "doblara", "2s": "doblaras", "3s": "doblara", "1p": "dobláramos", "2p": "doblarais", "3p": "doblaran"}, "dormir": {"1s": "durmiera", "2s": "durmieras", "3s": "durmiera", "1p": "durmiéramos", "2p": "durmierais", "3p": "durmieran"}, "dormirse": {"1s": "me durmiera", "2s": "te durmieras", "3s": "se durmiera", "1p": "nos durmiéramos", "2p": "os durmierais", "3p": "se durmieran"}, "duchar": {"1s": "duchara", "2s": "ducharas", "3s": "duchara", "1p": "ducháramos", "2p": "ducharais", "3p": "ducharan"}, "ducharse": {"1s": "me duchara", "2s": "te ducharas", "3s": "se duchara", "1p": "nos ducháramos", "2p": "os ducharais", "3p": "se ducharan"}, "dudar": {"1s": "dudara", "2s": "dudaras", "3s": "dudara", "1p": "dudáramos", "2p": "dudarais", "3p": "dudaran"}, "durar": {"1s": "durara", "2s": "duraras", "3s": "durara", "1p": "duráramos", "2p": "durarais", "3p": "duraran"}, "echar": {"1s": "echara", "2s": "echaras", "3s": "echara", "1p": "echáramos", "2p": "echarais", "3p": "echaran"}, "echarse": {"1s": "me echara", "2s": "te echaras", "3s": "se echara", "1p": "nos echáramos", "2p": "os echarais", "3p": "se echaran"}, "educar": {"1s": "educara", "2s": "educaras", "3s": "educara", "1p": "educáramos", "2p": "educarais", "3p": "educaran"}, "efectuar": {"1s": "efectuara", "2s": "efectuaras", "3s": "efectuara", "1p": "efectuáramos", "2p": "efectuarais", "3p": "efectuaran"}, "ejercer": {"1s": "ejerciera", "2s": "ejercieras", "3s": "ejerciera", "1p": "ejerciéramos", "2p": "ejercierais", "3p": "ejercieran"}, "elegir": {"1s": "eligiera", "2s": "eligieras", "3s": "eligiera", "1p": "eligiéramos", "2p": "eligierais", "3p": "eligieran"}, "eliminar": {"1s": "eliminara", "2s": "eliminaras", "3s": "eliminara", "1p": "elimináramos", "2p": "eliminarais", "3p": "eliminaran"}, "emborrachar": {"1s": "emborrachara", "2s": "emborracharas", "3s": "emborrachara", "1p": "emborracháramos", "2p": "emborracharais", "3p": "emborracharan"}, "emborracharse": {"1s": "me emborrachara", "2s": "te emborracharas", "3s": "se emborrachara", "1p": "nos emborracháramos", "2p": "os emborracharais", "3p": "se emborracharan"}, "emigrar": {"1s": "emigrara", "2s": "emigraras", "3s": "emigrara", "1p": "emigráramos", "2p": "emigrarais", "3p": "emigraran"}, "empezar": {"1s": "empezara", "2s": "empezaras", "3s": "empezara", "1p": "empezáramos", "2p": "empezarais", "3p": "empezaran"}, "emplear": {"1s": "empleara", "2s": "emplearas", "3s": "empleara", "1p": "empleáramos", "2p": "emplearais", "3p": "emplearan"}, "enamorar": {"1s": "enamorara", "2s": "enamoraras", "3s": "enamorara", "1p": "enamoráramos", "2p": "enamorarais", "3p": "enamoraran"}, "enamorarse": {"1s": "me enamorara", "2s": "te enamoraras", "3s": "se enamorara", "1p": "nos enamoráramos", "2p": "os enamorarais", "3p": "se enamoraran"}, "encantar": {"1s": "encantara", "2s": "encantaras", "3s": "encantara", "1p": "encantáramos", "2p": "encantarais", "3p": "encantaran"}, "encender": {"1s": "encendiera", "2s": "encendieras", "3s": "encendiera", "1p": "encendiéramos", "2p": "encendierais", "3p": "encendieran"}, "encontrar": {"1s": "encontrara", "2s": "encontraras", "3s": "encontrara", "1p": "encontráramos", "2p": "encontrarais", "3p": "encontraran"}, "enfadar": {"1s": "enfadara", "2s": "enfadaras", "3s": "enfadara", "1p": "enfadáramos", "2p": "enfadarais", "3p": "enfadaran"}, "enfadarse": {"1s": "me enfadara", "2s": "te enfadaras", "3s": "se enfadara", "1p": "nos enfadáramos", "2p": "os enfadarais", "3p": "se enfadaran"}, "enfermar": {"1s": "enfermara", "2s": "enfermaras", "3s": "enfermara", "1p": "enfermáramos", "2p": "enfermarais", "3p": "enfermaran"}, "enfermarse": {"1s": "me enfermara", "2s": "te enfermaras", "3s": "se enfermara", "1p": "nos enfermáramos", "2p": "os enfermarais", "3p": "se enfermaran"}, "enflaquecer": {"1s": "enflaqueciera", "2s": "enflaquecieras", "3s": "enflaqueciera", "1p": "enflaqueciéramos", "2p": "enflaquecierais", "3p": "enflaquecieran"}, "enflaquecerse": {"1s": "me enflaqueciera", "2s": "te enflaquecieras", "3s": "se enflaqueciera", "1p": "nos enflaqueciéramos", "2p": "os enflaquecierais", "3p": "se enflaquecieran"}, "engañar": {"1s": "engañara", "2s": "engañaras", "3s": "engañara", "1p": "engañáramos", "2p": "engañarais", "3p": "engañaran"}, "enojar": {"1s": "enojara", "2s": "enojaras", "3s": "enojara", "1p": "enojáramos", "2p": "enojarais", "3p": "enojaran"}, "enojarse": {"1s": "me enojara", "2s": "te enojaras", "3s": "se enojara", "1p": "nos enojáramos", "2p": "os enojarais", "3p": "se enojaran"}, "enriquecer": {"1s": "enriqueciera", "2s": "enriquecieras", "3s": "enriqueciera", "1p": "enriqueciéramos", "2p": "enriquecierais", "3p": "enriquecieran"}, "enriquecerse": {"1s": "me enriqueciera", "2s": "te enriquecieras", "3s": "se enriqueciera", "1p": "nos enriqueciéramos", "2p": "os enriquecierais", "3p": "se enriquecieran"}, "enseñar": {"1s": "enseñara", "2s": "enseñaras", "3s": "enseñara", "1p": "enseñáramos", "2p": "enseñarais", "3p": "enseñaran"}, "ensuciar": {"1s": "ensuciara", "2s": "ensuciaras", "3s": "ensuciara", "1p": "ensuciáramos", "2p": "ensuciarais", "3p": "ensuciaran"}, "entender": {"1s": "entendiera", "2s": "entendieras", "3s": "entendiera", "1p": "entendiéramos", "2p": "entendierais", "3p": "entendieran"}, "enterarse": {"1s": "me enterara", "2s": "te enteraras", "3s": "se enterara", "1p": "nos enteráramos", "2p": "os enterarais", "3p": "se enteraran"}, "entrar": {"1s": "entrara", "2s": "entraras", "3s": "entrara", "1p": "entráramos", "2p": "entrarais", "3p": "entraran"}, "entregar": {"1s": "entregara", "2s": "entregaras", "3s": "entregara", "1p": "entregáramos", "2p": "entregarais", "3p": "entregaran"}, "entretener": {"1s": "entretuviera", "2s": "entretuvieras", "3s": "entretuviera", "1p": "entretuviéramos", "2p": "entretuvierais", "3p": "entretuvieran"}, "entrevistar": {"1s": "entrevistara", "2s": "entrevistaras", "3s": "entrevistara", "1p": "entrevistáramos", "2p": "entrevistarais", "3p": "entrevistaran"}, "entusiasmar": {"1s": "entusiasmara", "2s": "entusiasmaras", "3s": "entusiasmara", "1p": "entusiasmáramos", "2p": "entusiasmarais", "3p": "entusiasmaran"}, "entusiasmarse": {"1s": "me entusiasmara", "2s": "te entusiasmaras", "3s": "se entusiasmara", "1p": "nos entusiasmáramos", "2p": "os entusiasmarais", "3p": "se entusiasmaran"}, "esconder": {"1s": "escondiera", "2s": "escondieras", "3s": "escondiera", "1p": "escondiéramos", "2p": "escondierais", "3p": "escondieran"}, "envejecer": {"1s": "envejeciera", "2s": "envejecieras", "3s": "envejeciera", "1p": "envejeciéramos", "2p": "envejecierais", "3p": "envejecieran"}, "envejecerse": {"1s": "me envejeciera", "2s": "te envejecieras", "3s": "se envejeciera", "1p": "nos envejeciéramos", "2p": "os envejecierais", "3p": "se envejecieran"}, "enviar": {"1s": "enviara", "2s": "enviaras", "3s": "enviara", "1p": "enviáramos", "2p": "enviarais", "3p": "enviaran"}, "equivocar": {"1s": "equivocara", "2s": "equivocaras", "3s": "equivocara", "1p": "equivocáramos", "2p": "equivocarais", "3p": "equivocaran"}, "equivocarse": {"1s": "me equivocara", "2s": "te equivocaras", "3s": "se equivocara", "1p": "nos equivocáramos", "2p": "os equivocarais", "3p": "se equivocaran"}, "errar": {"1s": "errara", "2s": "erraras", "3s": "errara", "1p": "erráramos", "2p": "errarais", "3p": "erraran"}, "escoger": {"1s": "escogiera", "2s": "escogieras", "3s": "escogiera", "1p": "escogiéramos", "2p": "escogierais", "3p": "escogieran"}, "esconderse": {"1s": "me escondiera", "2s": "te escondieras", "3s": "se escondiera", "1p": "nos escondiéramos", "2p": "os escondierais", "3p": "se escondieran"}, "escribir": {"1s": "escribiera", "2s": "escribieras", "3s": "escribiera", "1p": "escribiéramos", "2p": "escribierais", "3p": "escribieran"}, "escuchar": {"1s": "escuchara", "2s": "escucharas", "3s": "escuchara", "1p": "escucháramos", "2p": "escucharais", "3p": "escucharan"}, "esquiar": {"1s": "esquiara", "2s": "esquiaras", "3s": "esquiara", "1p": "esquiáramos", "2p": "esquiarais", "3p": "esquiaran"}, "establecer": {"1s": "estableciera", "2s": "establecieras", "3s": "estableciera", "1p": "estableciéramos", "2p": "establecierais", "3p": "establecieran"}, "estar": {"1s": "estuviera", "2s": "estuvieras", "3s": "estuviera", "1p": "estuviéramos", "2p": "estuvierais", "3p": "estuvieran"}, "estimar": {"1s": "estimara", "2s": "estimaras", "3s": "estimara", "1p": "estimáramos", "2p": "estimarais", "3p": "estimaran"}, "estudiar": {"1s": "estudiara", "2s": "estudiaras", "3s": "estudiara", "1p": "estudiáramos", "2p": "estudiarais", "3p": "estudiaran"}, "evacuar": {"1s": "evacuara", "2s": "evacuaras", "3s": "evacuara", "1p": "evacuáramos", "2p": "evacuarais", "3p": "evacuaran"}, "evitar": {"1s": "evitara", "2s": "evitaras", "3s": "evitara", "1p": "evitáramos", "2p": "evitarais", "3p": "evitaran"}, "exhibir": {"1s": "exhibiera", "2s": "exhibieras", "3s": "exhibiera", "1p": "exhibiéramos", "2p": "exhibierais", "3p": "exhibieran"}, "exigir": {"1s": "exigiera", "2s": "exigieras", "3s": "exigiera", "1p": "exigiéramos", "2p": "exigierais", "3p": "exigieran"}, "explicar": {"1s": "explicara", "2s": "explicaras", "3s": "explicara", "1p": "explicáramos", "2p": "explicarais", "3p": "explicaran"}, "explorar": {"1s": "explorara", "2s": "exploraras", "3s": "explorara", "1p": "exploráramos", "2p": "explorarais", "3p": "exploraran"}, "explotar": {"1s": "explotara", "2s": "explotaras", "3s": "explotara", "1p": "explotáramos", "2p": "explotarais", "3p": "explotaran"}, "exponer": {"1s": "expusiera", "2s": "expusieras", "3s": "expusiera", "1p": "expusiéramos", "2p": "expusierais", "3p": "expusieran"}, "exportar": {"1s": "exportara", "2s": "exportaras", "3s": "exportara", "1p": "exportáramos", "2p": "exportarais", "3p": "exportaran"}, "expresar": {"1s": "expresara", "2s": "expresaras", "3s": "expresara", "1p": "expresáramos", "2p": "expresarais", "3p": "expresaran"}, "extender": {"1s": "extendiera", "2s": "extendieras", "3s": "extendiera", "1p": "extendiéramos", "2p": "extendierais", "3p": "extendieran"}, "extinguir": {"1s": "extinguiera", "2s": "extinguieras", "3s": "extinguiera", "1p": "extinguiéramos", "2p": "extinguierais", "3p": "extinguieran"}, "fabricar": {"1s": "fabricara", "2s": "fabricaras", "3s": "fabricara", "1p": "fabricáramos", "2p": "fabricarais", "3p": "fabricaran"}, "faltar": {"1s": "faltara", "2s": "faltaras", "3s": "faltara", "1p": "faltáramos", "2p": "faltarais", "3p": "faltaran"}, "fascinar": {"1s": "fascinara", "2s": "fascinaras", "3s": "fascinara", "1p": "fascináramos", "2p": "fascinarais", "3p": "fascinaran"}, "felicitar": {"1s": "felicitara", "2s": "felicitaras", "3s": "felicitara", "1p": "felicitáramos", "2p": "felicitarais", "3p": "felicitaran"}, "fijar": {"1s": "fijara", "2s": "fijaras", "3s": "fijara", "1p": "fijáramos", "2p": "fijarais", "3p": "fijaran"}, "fingir": {"1s": "fingiera", "2s": "fingieras", "3s": "fingiera", "1p": "fingiéramos", "2p": "fingierais", "3p": "fingieran"}, "firmar": {"1s": "firmara", "2s": "firmaras", "3s": "firmara", "1p": "firmáramos", "2p": "firmarais", "3p": "firmaran"}, "florecer": {"1s": "floreciera", "2s": "florecieras", "3s": "floreciera", "1p": "floreciéramos", "2p": "florecierais", "3p": "florecieran"}, "formar": {"1s": "formara", "2s": "formaras", "3s": "formara", "1p": "formáramos", "2p": "formarais", "3p": "formaran"}, "fortalecer": {"1s": "fortaleciera", "2s": "fortalecieras", "3s": "fortaleciera", "1p": "fortaleciéramos", "2p": "fortalecierais", "3p": "fortalecieran"}, "freír": {"1s": "friera", "2s": "frieras", "3s": "friera", "1p": "friéramos", "2p": "frierais", "3p": "frieran"}, "fumar": {"1s": "fumara", "2s": "fumaras", "3s": "fumara", "1p": "fumáramos", "2p": "fumarais", "3p": "fumaran"}, "funcionar": {"1s": "funcionara", "2s": "funcionaras", "3s": "funcionara", "1p": "funcionáramos", "2p": "funcionarais", "3p": "funcionaran"}, "ganar": {"1s": "ganara", "2s": "ganaras", "3s": "ganara", "1p": "ganáramos", "2p": "ganarais", "3p": "ganaran"}, "gastar": {"1s": "gastara", "2s": "gastaras", "3s": "gastara", "1p": "gastáramos", "2p": "gastarais", "3p": "gastaran"}, "generalizar": {"1s": "generalizara", "2s": "generalizaras", "3s": "generalizara", "1p": "generalizáramos", "2p": "generalizarais", "3p": "generalizaran"}, "glorificar": {"1s": "glorificara", "2s": "glorificaras", "3s": "glorificara", "1p": "glorificáramos", "2p": "glorificarais", "3p": "glorificaran"}, "gobernar": {"1s": "gobernara", "2s": "gobernaras", "3s": "gobernara", "1p": "gobernáramos", "2p": "gobernarais", "3p": "gobernaran"}, "graduar": {"1s": "graduara", "2s": "graduaras", "3s": "graduara", "1p": "graduáramos", "2p": "graduarais", "3p": "graduaran"}, "graduarse": {"1s": "me graduara", "2s": "te graduaras", "3s": "se graduara", "1p": "nos graduáramos", "2p": "os graduarais", "3p": "se graduaran"}, "gritar": {"1s": "gritara", "2s": "gritaras", "3s": "gritara", "1p": "gritáramos", "2p": "gritarais", "3p": "gritaran"}, "gruñir": {"1s": "gruñera", "2s": "gruñeras", "3s": "gruñera", "1p": "gruñéramos", "2p": "gruñerais", "3p": "gruñeran"}, "guardar": {"1s": "guardara", "2s": "guardaras", "3s": "guardara", "1p": "guardáramos", "2p": "guardarais", "3p": "guardaran"}, "guiar": {"1s": "guiara", "2s": "guiaras", "3s": "guiara", "1p": "guiáramos", "2p": "guiarais", "3p": "guiaran"}, "gustar": {"1s": "gustara", "2s": "gustaras", "3s": "gustara", "1p": "gustáramos", "2p": "gustarais", "3p": "gustaran"}, "hablar": {"1s": "hablara", "2s": "hablaras", "3s": "hablara", "1p": "habláramos", "2p": "hablarais", "3p": "hablaran"}, "hacer": {"1s": "hiciera", "2s": "hicieras", "3s": "hiciera", "1p": "hiciéramos", "2p": "hicierais", "3p": "hicieran"}, "hallar": {"1s": "hallara", "2s": "hallaras", "3s": "hallara", "1p": "halláramos", "2p": "hallarais", "3p": "hallaran"}, "hallarse": {"1s": "me hallara", "2s": "te hallaras", "3s": "se hallara", "1p": "nos halláramos", "2p": "os hallarais", "3p": "se hallaran"}, "helar": {"1s": "helara", "2s": "helaras", "3s": "helara", "1p": "heláramos", "2p": "helarais", "3p": "helaran"}, "heredar": {"1s": "heredara", "2s": "heredaras", "3s": "heredara", "1p": "heredáramos", "2p": "heredarais", "3p": "heredaran"}, "herir": {"1s": "hiriera", "2s": "hirieras", "3s": "hiriera", "1p": "hiriéramos", "2p": "hirierais", "3p": "hirieran"}, "hervir": {"1s": "hirviera", "2s": "hirvieras", "3s": "hirviera", "1p": "hirviéramos", "2p": "hirvierais", "3p": "hirvieran"}, "huir": {"1s": "huyera", "2s": "huyeras", "3s": "huyera", "1p": "huyéramos", "2p": "huyerais", "3p": "huyeran"}, "ilustrar": {"1s": "ilustrara", "2s": "ilustraras", "3s": "ilustrara", "1p": "ilustráramos", "2p": "ilustrarais", "3p": "ilustraran"}, "importar": {"1s": "importara", "2s": "importaras", "3s": "importara", "1p": "importáramos", "2p": "importarais", "3p": "importaran"}, "imprimir": {"1s": "imprimiera", "2s": "imprimieras", "3s": "imprimiera", "1p": "imprimiéramos", "2p": "imprimierais", "3p": "imprimieran"}, "incluir": {"1s": "incluyera", "2s": "incluyeras", "3s": "incluyera", "1p": "incluyéramos", "2p": "incluyerais", "3p": "incluyeran"}, "indicar": {"1s": "indicara", "2s": "indicaras", "3s": "indicara", "1p": "indicáramos", "2p": "indicarais", "3p": "indicaran"}, "inducir": {"1s": "indujera", "2s": "indujeras", "3s": "indujera", "1p": "indujéramos", "2p": "indujerais", "3p": "indujeran"}, "influir": {"1s": "influyera", "2s": "influyeras", "3s": "influyera", "1p": "influyéramos", "2p": "influyerais", "3p": "influyeran"}, "informar": {"1s": "informara", "2s": "informaras", "3s": "informara", "1p": "informáramos", "2p": "informarais", "3p": "informaran"}, "iniciar": {"1s": "iniciara", "2s": "iniciaras", "3s": "iniciara", "1p": "iniciáramos", "2p": "iniciarais", "3p": "iniciaran"}, "inmigrar": {"1s": "inmigrara", "2s": "inmigraras", "3s": "inmigrara", "1p": "inmigráramos", "2p": "inmigrarais", "3p": "inmigraran"}, "insistir": {"1s": "insistiera", "2s": "insistieras", "3s": "insistiera", "1p": "insistiéramos", "2p": "insistierais", "3p": "insistieran"}, "instalar": {"1s": "instalara", "2s": "instalaras", "3s": "instalara", "1p": "instaláramos", "2p": "instalarais", "3p": "instalaran"}, "insultar": {"1s": "insultara", "2s": "insultaras", "3s": "insultara", "1p": "insultáramos", "2p": "insultarais", "3p": "insultaran"}, "intentar": {"1s": "intentara", "2s": "intentaras", "3s": "intentara", "1p": "intentáramos", "2p": "intentarais", "3p": "intentaran"}, "interesar": {"1s": "interesara", "2s": "interesaras", "3s": "interesara", "1p": "interesáramos", "2p": "interesarais", "3p": "interesaran"}, "interpretar": {"1s": "interpretara", "2s": "interpretaras", "3s": "interpretara", "1p": "interpretáramos", "2p": "interpretarais", "3p": "interpretaran"}, "introducir": {"1s": "introdujera", "2s": "introdujeras", "3s": "introdujera", "1p": "introdujéramos", "2p": "introdujerais", "3p": "introdujeran"}, "invadir": {"1s": "invadiera", "2s": "invadieras", "3s": "invadiera", "1p": "invadiéramos", "2p": "invadierais", "3p": "invadieran"}, "inventar": {"1s": "inventara", "2s": "inventaras", "3s": "inventara", "1p": "inventáramos", "2p": "inventarais", "3p": "inventaran"}, "invertir": {"1s": "invirtiera", "2s": "invirtieras", "3s": "invirtiera", "1p": "invirtéramos", "2p": "invirtierais", "3p": "invirtieran"}, "investigar": {"1s": "investigara", "2s": "investigaras", "3s": "investigara", "1p": "investigáramos", "2p": "investigarais", "3p": "investigaran"}, "invitar": {"1s": "invitara", "2s": "invitaras", "3s": "invitara", "1p": "invitáramos", "2p": "invitarais", "3p": "invitaran"}, "invocar": {"1s": "invocara", "2s": "invocaras", "3s": "invocara", "1p": "invocáramos", "2p": "invocarais", "3p": "invocaran"}, "ir": {"1s": "fuera", "2s": "fueras", "3s": "fuera", "1p": "fuéramos", "2p": "fuerais", "3p": "fueran"}, "irse": {"1s": "me fuera", "2s": "te fueras", "3s": "se fuera", "1p": "nos fuéramos", "2p": "os fuerais", "3p": "se fueran"}, "jactarse": {"1s": "me jactara", "2s": "te jactaras", "3s": "se jactara", "1p": "nos jactáramos", "2p": "os jactarais", "3p": "se jactaran"}, "jugar": {"1s": "jugara", "2s": "jugaras", "3s": "jugara", "1p": "jugáramos", "2p": "jugarais", "3p": "jugaran"}, "juntar": {"1s": "juntara", "2s": "juntaras", "3s": "juntara", "1p": "juntáramos", "2p": "juntarais", "3p": "juntaran"}, "juntarse": {"1s": "me juntara", "2s": "te juntaras", "3s": "se juntara", "1p": "nos juntáramos", "2p": "os juntarais", "3p": "se juntaran"}, "jurar": {"1s": "jurara", "2s": "juraras", "3s": "jurara", "1p": "juráramos", "2p": "jurarais", "3p": "juraran"}, "ladrar": {"1s": "ladrara", "2s": "ladraras", "3s": "ladrara", "1p": "ladráramos", "2p": "ladrarais", "3p": "ladraran"}, "lamentar": {"1s": "lamentara", "2s": "lamentaras", "3s": "lamentara", "1p": "lamentáramos", "2p": "lamentarais", "3p": "lamentaran"}, "lanzar": {"1s": "lanzara", "2s": "lanzaras", "3s": "lanzara", "1p": "lanzáramos", "2p": "lanzarais", "3p": "lanzaran"}, "lastimar": {"1s": "lastimara", "2s": "lastimaras", "3s": "lastimara", "1p": "lastimáramos", "2p": "lastimarais", "3p": "lastimaran"}, "lavar": {"1s": "lavara", "2s": "lavaras", "3s": "lavara", "1p": "laváramos", "2p": "lavarais", "3p": "lavaran"}, "lavarse": {"1s": "me lavara", "2s": "te lavaras", "3s": "se lavara", "1p": "nos laváramos", "2p": "os lavarais", "3p": "se lavaran"}, "leer": {"1s": "leyera", "2s": "leyeras", "3s": "leyera", "1p": "leyéramos", "2p": "leyerais", "3p": "leyeran"}, "legalizar": {"1s": "legalizara", "2s": "legalizaras", "3s": "legalizara", "1p": "legalizáramos", "2p": "legalizarais", "3p": "legalizaran"}, "levantar": {"1s": "levantara", "2s": "levantaras", "3s": "levantara", "1p": "levantáramos", "2p": "levantarais", "3p": "levantaran"}, "levantarse": {"1s": "me levantara", "2s": "te levantaras", "3s": "se levantara", "1p": "nos levantáramos", "2p": "os levantarais", "3p": "se levantaran"}, "limpiar": {"1s": "limpiara", "2s": "limpiaras", "3s": "limpiara", "1p": "limpiáramos", "2p": "limpiarais", "3p": "limpiaran"}, "llamar": {"1s": "llamara", "2s": "llamaras", "3s": "llamara", "1p": "llamáramos", "2p": "llamarais", "3p": "llamaran"}, "llamarse": {"1s": "me llamara", "2s": "te llamaras", "3s": "se llamara", "1p": "nos llamáramos", "2p": "os llamarais", "3p": "se llamaran"}, "llegar": {"1s": "llegara", "2s": "llegaras", "3s": "llegara", "1p": "llegáramos", "2p": "llegarais", "3p": "llegaran"}, "llenar": {"1s": "llenara", "2s": "llenaras", "3s": "llenara", "1p": "llenáramos", "2p": "llenarais", "3p": "llenaran"}, "llevar": {"1s": "llevara", "2s": "llevaras", "3s": "llevara", "1p": "lleváramos", "2p": "llevarais", "3p": "llevaran"}, "llorar": {"1s": "llorara", "2s": "lloraras", "3s": "llorara", "1p": "lloráramos", "2p": "llorarais", "3p": "lloraran"}, "llover": {"1s": "", "2s": "", "3s": "lloviera", "1p": "", "2p": "", "3p": ""}, "lograr": {"1s": "lograra", "2s": "lograras", "3s": "lograra", "1p": "lográramos", "2p": "lograrais", "3p": "lograran"}, "luchar": {"1s": "luchara", "2s": "lucharas", "3s": "luchara", "1p": "lucháramos", "2p": "lucharais", "3p": "lucharan"}, "madurar": {"1s": "madurara", "2s": "maduraras", "3s": "madurara", "1p": "maduráramos", "2p": "madurarais", "3p": "maduraran"}, "mandar": {"1s": "mandara", "2s": "mandaras", "3s": "mandara", "1p": "mandáramos", "2p": "mandarais", "3p": "mandaran"}, "manejar": {"1s": "manejara", "2s": "manejaras", "3s": "manejara", "1p": "manejáramos", "2p": "manejarais", "3p": "manejaran"}, "mantener": {"1s": "mantuviera", "2s": "mantuvieras", "3s": "mantuviera", "1p": "mantuviéramos", "2p": "mantuvierais", "3p": "mantuvieran"}, "maquillar": {"1s": "maquillara", "2s": "maquillaras", "3s": "maquillara", "1p": "maquilláramos", "2p": "maquillarais", "3p": "maquillaran"}, "maquillarse": {"1s": "me maquillara", "2s": "te maquillaras", "3s": "se maquillara", "1p": "nos maquilláramos", "2p": "os maquillarais", "3p": "se maquillaran"}, "marcar": {"1s": "marcara", "2s": "marcaras", "3s": "marcara", "1p": "marcáramos", "2p": "marcarais", "3p": "marcaran"}, "masticar": {"1s": "masticara", "2s": "masticaras", "3s": "masticara", "1p": "masticáramos", "2p": "masticarais", "3p": "masticaran"}, "matar": {"1s": "matara", "2s": "mataras", "3s": "matara", "1p": "matáramos", "2p": "matarais", "3p": "mataran"}, "matricular": {"1s": "matriculara", "2s": "matricularas", "3s": "matriculara", "1p": "matriculáramos", "2p": "matricularais", "3p": "matricularan"}, "matricularse": {"1s": "me matriculara", "2s": "te matricularas", "3s": "se matriculara", "1p": "nos matriculáramos", "2p": "os matricularais", "3p": "se matricularan"}, "medir": {"1s": "midiera", "2s": "midieras", "3s": "midiera", "1p": "midiéramos", "2p": "midierais", "3p": "midieran"}, "mentir": {"1s": "mintiera", "2s": "mintieras", "3s": "mintiera", "1p": "mintiéramos", "2p": "mintierais", "3p": "mintieran"}, "merecer": {"1s": "mereciera", "2s": "merecieras", "3s": "mereciera", "1p": "mereciéramos", "2p": "merecierais", "3p": "merecieran"}, "merendar": {"1s": "merendara", "2s": "merendaras", "3s": "merendara", "1p": "merendáramos", "2p": "merendarais", "3p": "merendaran"}, "meter": {"1s": "metiera", "2s": "metieras", "3s": "metiera", "1p": "metiéramos", "2p": "metierais", "3p": "metieran"}, "mezclar": {"1s": "mezclara", "2s": "mezclaras", "3s": "mezclara", "1p": "mezcláramos", "2p": "mezclarais", "3p": "mezclaran"}, "mirar": {"1s": "mirara", "2s": "miraras", "3s": "mirara", "1p": "miráramos", "2p": "mirarais", "3p": "miraran"}, "modificar": {"1s": "modificara", "2s": "modificaras", "3s": "modificara", "1p": "modificáramos", "2p": "modificarais", "3p": "modificaran"}, "molestar": {"1s": "molestara", "2s": "molestaras", "3s": "molestara", "1p": "molestáramos", "2p": "molestarais", "3p": "molestaran"}, "montar": {"1s": "montara", "2s": "montaras", "3s": "montara", "1p": "montáramos", "2p": "montarais", "3p": "montaran"}, "morir": {"1s": "muriera", "2s": "murieras", "3s": "muriera", "1p": "muriéramos", "2p": "murierais", "3p": "murieran"}, "mostrar": {"1s": "mostrara", "2s": "mostraras", "3s": "mostrara", "1p": "mostráramos", "2p": "mostrarais", "3p": "mostraran"}, "mover": {"1s": "moviera", "2s": "movieras", "3s": "moviera", "1p": "moviéramos", "2p": "movierais", "3p": "movieran"}, "moverse": {"1s": "me moviera", "2s": "te movieras", "3s": "se moviera", "1p": "nos moviéramos", "2p": "os movierais", "3p": "se movieran"}, "mudar(se)": {"1s": "mudara", "2s": "mudaras", "3s": "mudara", "1p": "mudáramos", "2p": "mudarais", "3p": "mudaran"}, "mudarse": {"1s": "me mudara", "2s": "te mudaras", "3s": "se mudara", "1p": "nos mudáramos", "2p": "os mudarais", "3p": "se mudaran"}, "nacer": {"1s": "naciera", "2s": "nacieras", "3s": "naciera", "1p": "naciéramos", "2p": "nacierais", "3p": "nacieran"}, "nadar": {"1s": "nadara", "2s": "nadaras", "3s": "nadara", "1p": "nadáramos", "2p": "nadarais", "3p": "nadaran"}, "navegar": {"1s": "navegara", "2s": "navegaras", "3s": "navegara", "1p": "navegáramos", "2p": "navegarais", "3p": "navegaran"}, "necesitar": {"1s": "necesitara", "2s": "necesitaras", "3s": "necesitara", "1p": "necesitáramos", "2p": "necesitarais", "3p": "necesitaran"}, "negar": {"1s": "negara", "2s": "negaras", "3s": "negara", "1p": "negáramos", "2p": "negarais", "3p": "negaran"}, "negarse": {"1s": "me negara", "2s": "te negaras", "3s": "se negara", "1p": "nos negáramos", "2p": "os negarais", "3p": "se negaran"}, "negociar": {"1s": "negociara", "2s": "negociaras", "3s": "negociara", "1p": "negociáramos", "2p": "negociarais", "3p": "negociaran"}, "nevar": {"1s": "", "2s": "", "3s": "nevara", "1p": "", "2p": "", "3p": ""}, "notar": {"1s": "notara", "2s": "notaras", "3s": "notara", "1p": "notáramos", "2p": "notarais", "3p": "notaran"}, "obedecer": {"1s": "obedeciera", "2s": "obedecieras", "3s": "obedeciera", "1p": "obedeciéramos", "2p": "obedecierais", "3p": "obedecieran"}, "obligar": {"1s": "obligara", "2s": "obligaras", "3s": "obligara", "1p": "obligáramos", "2p": "obligarais", "3p": "obligaran"}, "obtener": {"1s": "obtuviera", "2s": "obtuvieras", "3s": "obtuviera", "1p": "obtuviéramos", "2p": "obtuvierais", "3p": "obtuvieran"}, "ocurrir": {"1s": "", "2s": "", "3s": "ocurriera", "1p": "", "2p": "", "3p": "ocurrieran"}, "odiar": {"1s": "odiara", "2s": "odiaras", "3s": "odiara", "1p": "odiáramos", "2p": "odiarais", "3p": "odiaran"}, "ofender": {"1s": "ofendiera", "2s": "ofendieras", "3s": "ofendiera", "1p": "ofendiéramos", "2p": "ofendierais", "3p": "ofendieran"}, "ofrecer": {"1s": "ofreciera", "2s": "ofrecieras", "3s": "ofreciera", "1p": "ofreciéramos", "2p": "ofrecierais", "3p": "ofrecieran"}, "oír": {"1s": "oyera", "2s": "oyeras", "3s": "oyera", "1p": "oyéramos", "2p": "oyerais", "3p": "oyeran"}, "oler": {"1s": "oliera", "2s": "olieras", "3s": "oliera", "1p": "oliéramos", "2p": "olierais", "3p": "olieran"}, "olvidar": {"1s": "olvidara", "2s": "olvidaras", "3s": "olvidara", "1p": "olvidáramos", "2p": "olvidarais", "3p": "olvidaran"}, "olvidarse": {"1s": "me olvidara", "2s": "te olvidaras", "3s": "se olvidara", "1p": "nos olvidáramos", "2p": "os olvidarais", "3p": "se olvidaran"}, "oponer": {"1s": "opusiera", "2s": "opusieras", "3s": "opusiera", "1p": "opusiéramos", "2p": "opusierais", "3p": "opusieran"}, "oponerse": {"1s": "me opusiera", "2s": "te opusieras", "3s": "se opusiera", "1p": "nos opusiéramos", "2p": "os opusierais", "3p": "se opusieran"}, "organizar": {"1s": "organizara", "2s": "organizaras", "3s": "organizara", "1p": "organizáramos", "2p": "organizarais", "3p": "organizaran"}, "padecer": {"1s": "padeciera", "2s": "padecieras", "3s": "padeciera", "1p": "padeciéramos", "2p": "padecierais", "3p": "padecieran"}, "pagar": {"1s": "pagara", "2s": "pagaras", "3s": "pagara", "1p": "pagáramos", "2p": "pagarais", "3p": "pagaran"}, "parar": {"1s": "parara", "2s": "pararas", "3s": "parara", "1p": "paráramos", "2p": "pararais", "3p": "pararan"}, "parecer": {"1s": "pareciera", "2s": "parecieras", "3s": "pareciera", "1p": "pareciéramos", "2p": "parecierais", "3p": "parecieran"}, "participar": {"1s": "participara", "2s": "participaras", "3s": "participara", "1p": "participáramos", "2p": "participarais", "3p": "participaran"}, "pasar": {"1s": "pasara", "2s": "pasaras", "3s": "pasara", "1p": "pasáramos", "2p": "pasarais", "3p": "pasaran"}, "patinar": {"1s": "patinara", "2s": "patinaras", "3s": "patinara", "1p": "patináramos", "2p": "patinarais", "3p": "patinaran"}, "pedir": {"1s": "pidiera", "2s": "pidieras", "3s": "pidiera", "1p": "pidiéramos", "2p": "pidierais", "3p": "pidieran"}, "pegar": {"1s": "pegara", "2s": "pegaras", "3s": "pegara", "1p": "pegáramos", "2p": "pegarais", "3p": "pegaran"}, "peinar": {"1s": "peinara", "2s": "peinaras", "3s": "peinara", "1p": "peináramos", "2p": "peinarais", "3p": "peinaran"}, "peinarse": {"1s": "me peinara", "2s": "te peinaras", "3s": "se peinara", "1p": "nos peináramos", "2p": "os peinarais", "3p": "se peinaran"}, "pelear": {"1s": "peleara", "2s": "pelearas", "3s": "peleara", "1p": "peleáramos", "2p": "pelearais", "3p": "pelearan"}, "pensar": {"1s": "pensara", "2s": "pensaras", "3s": "pensara", "1p": "pensáramos", "2p": "pensarais", "3p": "pensaran"}, "perder": {"1s": "perdiera", "2s": "perdieras", "3s": "perdiera", "1p": "perdiéramos", "2p": "perdierais", "3p": "perdieran"}, "perdonar": {"1s": "perdonara", "2s": "perdonaras", "3s": "perdonara", "1p": "perdonáramos", "2p": "perdonarais", "3p": "perdonaran"}, "permanecer": {"1s": "permaneciera", "2s": "permanecieras", "3s": "permaneciera", "1p": "permaneciéramos", "2p": "permanecierais", "3p": "permanecieran"}, "permitir": {"1s": "permitiera", "2s": "permitieras", "3s": "permitiera", "1p": "permitiéramos", "2p": "permitierais", "3p": "permitieran"}, "perseguir": {"1s": "persiguiera", "2s": "persiguieras", "3s": "persiguiera", "1p": "persiguiéramos", "2p": "persiguierais", "3p": "persiguieran"}, "pertenecer": {"1s": "perteneciera", "2s": "pertenecieras", "3s": "perteneciera", "1p": "perteneciéramos", "2p": "pertenecierais", "3p": "pertenecieran"}, "pesar": {"1s": "pesara", "2s": "pesaras", "3s": "pesara", "1p": "pesáramos", "2p": "pesarais", "3p": "pesaran"}, "pescar": {"1s": "pescara", "2s": "pescaras", "3s": "pescara", "1p": "pescáramos", "2p": "pescarais", "3p": "pescaran"}, "picar": {"1s": "picara", "2s": "picaras", "3s": "picara", "1p": "picáramos", "2p": "picarais", "3p": "picaran"}, "pintar": {"1s": "pintara", "2s": "pintaras", "3s": "pintara", "1p": "pintáramos", "2p": "pintarais", "3p": "pintaran"}, "platicar": {"1s": "platicara", "2s": "platicaras", "3s": "platicara", "1p": "platicáramos", "2p": "platicarais", "3p": "platicaran"}, "planchar": {"1s": "planchara", "2s": "plancharas", "3s": "planchara", "1p": "plancháramos", "2p": "plancharais", "3p": "plancharan"}, "plantar": {"1s": "plantara", "2s": "plantaras", "3s": "plantara", "1p": "plantáramos", "2p": "plantarais", "3p": "plantaran"}, "poder": {"1s": "pudiera", "2s": "pudieras", "3s": "pudiera", "1p": "pudiéramos", "2p": "pudierais", "3p": "pudieran"}, "poner": {"1s": "pusiera", "2s": "pusieras", "3s": "pusiera", "1p": "pusiéramos", "2p": "pusierais", "3p": "pusieran"}, "ponerse": {"1s": "me pusiera", "2s": "te pusieras", "3s": "se pusiera", "1p": "nos pusiéramos", "2p": "os pusierais", "3p": "se pusieran"}, "practicar": {"1s": "practicara", "2s": "practicaras", "3s": "practicara", "1p": "practicáramos", "2p": "practicarais", "3p": "practicaran"}, "predecir": {"1s": "predijera", "2s": "predijeras", "3s": "predijera", "1p": "predijéramos", "2p": "predijerais", "3p": "predijeran"}, "preferir": {"1s": "prefiriera", "2s": "prefirieras", "3s": "prefiriera", "1p": "prefiriéramos", "2p": "prefirierais", "3p": "prefirieran"}, "preguntar": {"1s": "preguntara", "2s": "preguntaras", "3s": "preguntara", "1p": "preguntáramos", "2p": "preguntarais", "3p": "preguntaran"}, "preguntarse": {"1s": "me preguntara", "2s": "te preguntaras", "3s": "se preguntara", "1p": "nos preguntáramos", "2p": "os preguntarais", "3p": "se preguntaran"}, "preparar": {"1s": "preparara", "2s": "prepararas", "3s": "preparara", "1p": "preparáramos", "2p": "prepararais", "3p": "prepararan"}, "prepararse": {"1s": "me preparara", "2s": "te prepararas", "3s": "se preparara", "1p": "nos preparáramos", "2p": "os prepararais", "3p": "se prepararan"}, "presentir": {"1s": "presintiera", "2s": "presintieras", "3s": "presintiera", "1p": "presintéramos", "2p": "presintierais", "3p": "presintieran"}, "preservar": {"1s": "preservara", "2s": "preservaras", "3s": "preservara", "1p": "preserváramos", "2p": "preservarais", "3p": "preservaran"}, "prever": {"1s": "previera", "2s": "previeras", "3s": "previera", "1p": "previéramos", "2p": "previerais", "3p": "previeran"}, "probar": {"1s": "probara", "2s": "probaras", "3s": "probara", "1p": "probáramos", "2p": "probarais", "3p": "probaran"}, "producir": {"1s": "produjera", "2s": "produjeras", "3s": "produjera", "1p": "produjéramos", "2p": "produjerais", "3p": "produjeran"}, "prohibir": {"1s": "prohibiera", "2s": "prohibieras", "3s": "prohibiera", "1p": "prohibiéramos", "2p": "prohibierais", "3p": "prohibieran"}, "prometer": {"1s": "prometiera", "2s": "prometieras", "3s": "prometiera", "1p": "prometiéramos", "2p": "prometierais", "3p": "prometieran"}, "proponer": {"1s": "propusiera", "2s": "propusieras", "3s": "propusiera", "1p": "propusiéramos", "2p": "propusierais", "3p": "propusieran"}, "proseguir": {"1s": "prosiguiera", "2s": "prosiguieras", "3s": "prosiguiera", "1p": "prosiguiéramos", "2p": "prosiguierais", "3p": "prosiguieran"}, "proteger": {"1s": "protegiera", "2s": "protegieras", "3s": "protegiera", "1p": "protegiéramos", "2p": "protegierais", "3p": "protegieran"}, "protestar": {"1s": "protestara", "2s": "protestaras", "3s": "protestara", "1p": "protestáramos", "2p": "protestarais", "3p": "protestaran"}, "provocar": {"1s": "provocara", "2s": "provocaras", "3s": "provocara", "1p": "provocáramos", "2p": "provocarais", "3p": "provocaran"}, "publicar": {"1s": "publicara", "2s": "publicaras", "3s": "publicara", "1p": "publicáramos", "2p": "publicarais", "3p": "publicaran"}, "purificar": {"1s": "purificara", "2s": "purificaras", "3s": "purificara", "1p": "purificáramos", "2p": "purificarais", "3p": "purificaran"}, "quebrar": {"1s": "quebrara", "2s": "quebraras", "3s": "quebrara", "1p": "quebráramos", "2p": "quebrarais", "3p": "quebraran"}, "quebrarse": {"1s": "me quebrara", "2s": "te quebraras", "3s": "se quebrara", "1p": "nos quebráramos", "2p": "os quebrarais", "3p": "se quebraran"}, "quedar": {"1s": "quedara", "2s": "quedaras", "3s": "quedara", "1p": "quedáramos", "2p": "quedarais", "3p": "quedaran"}, "quedarse": {"1s": "me quedara", "2s": "te quedaras", "3s": "se quedara", "1p": "nos quedáramos", "2p": "os quedarais", "3p": "se quedaran"}, "quejarse": {"1s": "me quejara", "2s": "te quejaras", "3s": "se quejara", "1p": "nos quejáramos", "2p": "os quejarais", "3p": "se quejaran"}, "quemar": {"1s": "quemara", "2s": "quemaras", "3s": "quemara", "1p": "quemáramos", "2p": "quemarais", "3p": "quemaran"}, "quemarse": {"1s": "me quemara", "2s": "te quemaras", "3s": "se quemara", "1p": "nos quemáramos", "2p": "os quemarais", "3p": "se quemaran"}, "querer": {"1s": "quisiera", "2s": "quisieras", "3s": "quisiera", "1p": "quisiéramos", "2p": "quisierais", "3p": "quisieran"}, "realizar": {"1s": "realizara", "2s": "realizaras", "3s": "realizara", "1p": "realizáramos", "2p": "realizarais", "3p": "realizaran"}, "rechazar": {"1s": "rechazara", "2s": "rechazaras", "3s": "rechazara", "1p": "rechazáramos", "2p": "rechazarais", "3p": "rechazaran"}, "recibir": {"1s": "recibiera", "2s": "recibieras", "3s": "recibiera", "1p": "recibiéramos", "2p": "recibierais", "3p": "recibieran"}, "reciclar": {"1s": "reciclara", "2s": "reciclaras", "3s": "reciclara", "1p": "recicláramos", "2p": "reciclarais", "3p": "reciclaran"}, "recoger": {"1s": "recogiera", "2s": "recogieras", "3s": "recogiera", "1p": "recogiéramos", "2p": "recogierais", "3p": "recogieran"}, "recomendar": {"1s": "recomendara", "2s": "recomendaras", "3s": "recomendara", "1p": "recomendáramos", "2p": "recomendarais", "3p": "recomendaran"}, "reconocer": {"1s": "reconociera", "2s": "reconocieras", "3s": "reconociera", "1p": "reconociéramos", "2p": "reconocierais", "3p": "reconocieran"}, "recordar": {"1s": "recordara", "2s": "recordaras", "3s": "recordara", "1p": "recordáramos", "2p": "recordarais", "3p": "recordaran"}, "reducir": {"1s": "redujera", "2s": "redujeras", "3s": "redujera", "1p": "redujéramos", "2p": "redujerais", "3p": "redujeran"}, "regalar": {"1s": "regalara", "2s": "regalaras", "3s": "regalara", "1p": "regaláramos", "2p": "regalarais", "3p": "regalaran"}, "regar": {"1s": "regara", "2s": "regaras", "3s": "regara", "1p": "regáramos", "2p": "regarais", "3p": "regaran"}, "regatear": {"1s": "regateara", "2s": "regatearas", "3s": "regateara", "1p": "regateáramos", "2p": "regatearais", "3p": "regatearan"}, "regir": {"1s": "rigiera", "2s": "rigieras", "3s": "rigiera", "1p": "rigiéramos", "2p": "rigierais", "3p": "rigieran"}, "registrar": {"1s": "registrara", "2s": "registraras", "3s": "registrara", "1p": "registráramos", "2p": "registrarais", "3p": "registraran"}, "registrarse": {"1s": "me registrara", "2s": "te registraras", "3s": "se registrara", "1p": "nos registráramos", "2p": "os registrarais", "3p": "se registraran"}, "regresar": {"1s": "regresara", "2s": "regresaras", "3s": "regresara", "1p": "regresáramos", "2p": "regresarais", "3p": "regresaran"}, "regular": {"1s": "regulara", "2s": "regularas", "3s": "regulara", "1p": "reguláramos", "2p": "regularais", "3p": "regularan"}, "rehusar": {"1s": "rehusara", "2s": "rehusaras", "3s": "rehusara", "1p": "rehusáramos", "2p": "rehusarais", "3p": "rehusaran"}, "reinar": {"1s": "reinara", "2s": "reinaras", "3s": "reinara", "1p": "reináramos", "2p": "reinarais", "3p": "reinaran"}, "reír": {"1s": "riera", "2s": "rieras", "3s": "riera", "1p": "riéramos", "2p": "rierais", "3p": "rieran"}, "renacer": {"1s": "renaciera", "2s": "renacieras", "3s": "renaciera", "1p": "renaciéramos", "2p": "renacierais", "3p": "renacieran"}, "renovar": {"1s": "renovara", "2s": "renovaras", "3s": "renovara", "1p": "renováramos", "2p": "renovarais", "3p": "renovaran"}, "renunciar": {"1s": "renunciara", "2s": "renunciaras", "3s": "renunciara", "1p": "renunciáramos", "2p": "renunciarais", "3p": "renunciaran"}, "reñir": {"1s": "riñera", "2s": "riñeras", "3s": "riñera", "1p": "riñéramos", "2p": "riñerais", "3p": "riñeran"}, "reparar": {"1s": "reparara", "2s": "repararas", "3s": "reparara", "1p": "reparáramos", "2p": "repararais", "3p": "repararan"}, "repasar": {"1s": "repasara", "2s": "repasaras", "3s": "repasara", "1p": "repasáramos", "2p": "repasarais", "3p": "repasaran"}, "repetir": {"1s": "repitiera", "2s": "repitieras", "3s": "repitiera", "1p": "repitiéramos", "2p": "repitierais", "3p": "repitieran"}, "replicar": {"1s": "replicara", "2s": "replicaras", "3s": "replicara", "1p": "replicáramos", "2p": "replicarais", "3p": "replicaran"}, "reportar": {"1s": "reportara", "2s": "reportaras", "3s": "reportara", "1p": "reportáramos", "2p": "reportarais", "3p": "reportaran"}, "requerir": {"1s": "requiriera", "2s": "requirieras", "3s": "requiriera", "1p": "requiriéramos", "2p": "requirierais", "3p": "requirieran"}, "reservar": {"1s": "reservara", "2s": "reservaras", "3s": "reservara", "1p": "reserváramos", "2p": "reservarais", "3p": "reservaran"}, "resolver": {"1s": "resolviera", "2s": "resolvieras", "3s": "resolviera", "1p": "resolviéramos", "2p": "resolvierais", "3p": "resolvieran"}, "respetar": {"1s": "respetara", "2s": "respetaras", "3s": "respetara", "1p": "respetáramos", "2p": "respetarais", "3p": "respetaran"}, "respirar": {"1s": "respirara", "2s": "respiraras", "3s": "respirara", "1p": "respiráramos", "2p": "respirarais", "3p": "respiraran"}, "responder": {"1s": "respondiera", "2s": "respondieras", "3s": "respondiera", "1p": "respondiéramos", "2p": "respondierais", "3p": "respondieran"}, "resultar": {"1s": "resultara", "2s": "resultaras", "3s": "resultara", "1p": "resultáramos", "2p": "resultarais", "3p": "resultaran"}, "revelar": {"1s": "revelara", "2s": "revelaras", "3s": "revelara", "1p": "reveláramos", "2p": "revelarais", "3p": "revelaran"}, "rezar": {"1s": "rezara", "2s": "rezaras", "3s": "rezara", "1p": "rezáramos", "2p": "rezarais", "3p": "rezaran"}, "robar": {"1s": "robara", "2s": "robaras", "3s": "robara", "1p": "robáramos", "2p": "robarais", "3p": "robaran"}, "rogar": {"1s": "rogara", "2s": "rogaras", "3s": "rogara", "1p": "rogáramos", "2p": "rogarais", "3p": "rogaran"}, "romper": {"1s": "rompiera", "2s": "rompieras", "3s": "rompiera", "1p": "rompiéramos", "2p": "rompierais", "3p": "rompieran"}, "saber": {"1s": "supiera", "2s": "supieras", "3s": "supiera", "1p": "supiéramos", "2p": "supierais", "3p": "supieran"}, "sacar": {"1s": "sacara", "2s": "sacaras", "3s": "sacara", "1p": "sacáramos", "2p": "sacarais", "3p": "sacaran"}, "sacrificar": {"1s": "sacrificara", "2s": "sacrificaras", "3s": "sacrificara", "1p": "sacrificáramos", "2p": "sacrificarais", "3p": "sacrificaran"}, "sacudir": {"1s": "sacudiera", "2s": "sacudieras", "3s": "sacudiera", "1p": "sacudiéramos", "2p": "sacudierais", "3p": "sacudieran"}, "salir": {"1s": "saliera", "2s": "salieras", "3s": "saliera", "1p": "saliéramos", "2p": "salierais", "3p": "salieran"}, "saltar": {"1s": "saltara", "2s": "saltaras", "3s": "saltara", "1p": "saltáramos", "2p": "saltarais", "3p": "saltaran"}, "saludar": {"1s": "saludara", "2s": "saludaras", "3s": "saludara", "1p": "saludáramos", "2p": "saludarais", "3p": "saludaran"}, "salvar": {"1s": "salvara", "2s": "salvaras", "3s": "salvara", "1p": "salváramos", "2p": "salvarais", "3p": "salvaran"}, "satisfacer": {"1s": "satisficiera", "2s": "satisficieras", "3s": "satisficiera", "1p": "satisficiéramos", "2p": "satisficierais", "3p": "satisficieran"}, "satirizar": {"1s": "satirizara", "2s": "satirizaras", "3s": "satirizara", "1p": "satirizáramos", "2p": "satirizarais", "3p": "satirizaran"}, "secar": {"1s": "secara", "2s": "secaras", "3s": "secara", "1p": "secáramos", "2p": "secarais", "3p": "secaran"}, "secarse": {"1s": "me secara", "2s": "te secaras", "3s": "se secara", "1p": "nos secáramos", "2p": "os secarais", "3p": "se secaran"}, "seguir": {"1s": "siguiera", "2s": "siguieras", "3s": "siguiera", "1p": "siguiéramos", "2p": "siguierais", "3p": "siguieran"}, "sentar": {"1s": "sentara", "2s": "sentaras", "3s": "sentara", "1p": "sentáramos", "2p": "sentarais", "3p": "sentaran"}, "sentarse": {"1s": "me sentara", "2s": "te sentaras", "3s": "se sentara", "1p": "nos sentáramos", "2p": "os sentarais", "3p": "se sentaran"}, "sentir": {"1s": "sintiera", "2s": "sintieras", "3s": "sintiera", "1p": "sintiéramos", "2p": "sintierais", "3p": "sintieran"}, "sentirse": {"1s": "me sintiera", "2s": "te sintieras", "3s": "se sintiera", "1p": "nos sintiéramos", "2p": "os sintierais", "3p": "se sintieran"}, "señalar": {"1s": "señalara", "2s": "señalaras", "3s": "señalara", "1p": "señaláramos", "2p": "señalarais", "3p": "señalaran"}, "ser": {"1s": "fuera", "2s": "fueras", "3s": "fuera", "1p": "fuéramos", "2p": "fuerais", "3p": "fueran"}, "servir": {"1s": "sirviera", "2s": "sirvieras", "3s": "sirviera", "1p": "sirviéramos", "2p": "sirvierais", "3p": "sirvieran"}, "significar": {"1s": "significara", "2s": "significaras", "3s": "significara", "1p": "significáramos", "2p": "significarais", "3p": "significaran"}, "simbolizar": {"1s": "simbolizara", "2s": "simbolizaras", "3s": "simbolizara", "1p": "simbolizáramos", "2p": "simbolizarais", "3p": "simbolizaran"}, "situar": {"1s": "situara", "2s": "situaras", "3s": "situara", "1p": "situáramos", "2p": "situarais", "3p": "situaran"}, "sobrevivir": {"1s": "sobreviviera", "2s": "sobrevivieras", "3s": "sobreviviera", "1p": "sobreviviéramos", "2p": "sobrevivierais", "3p": "sobrevivieran"}, "soler": {"1s": "soliera", "2s": "solieras", "3s": "soliera", "1p": "soliéramos", "2p": "solierais", "3p": "solieran"}, "sonar": {"1s": "sonara", "2s": "sonaras", "3s": "sonara", "1p": "sonáramos", "2p": "sonarais", "3p": "sonaran"}, "soñar": {"1s": "soñara", "2s": "soñaras", "3s": "soñara", "1p": "soñáramos", "2p": "soñarais", "3p": "soñaran"}, "sonreír": {"1s": "sonriera", "2s": "sonrieras", "3s": "sonriera", "1p": "sonriéramos", "2p": "sonrierais", "3p": "sonrieran"}, "soportar": {"1s": "soportara", "2s": "soportaras", "3s": "soportara", "1p": "soportáramos", "2p": "soportarais", "3p": "soportaran"}, "sorprender": {"1s": "sorprendiera", "2s": "sorprendieras", "3s": "sorprendiera", "1p": "sorprendiéramos", "2p": "sorprendierais", "3p": "sorprendieran"}, "subir": {"1s": "subiera", "2s": "subieras", "3s": "subiera", "1p": "subiéramos", "2p": "subierais", "3p": "subieran"}, "suceder": {"1s": "sucediera", "2s": "sucedieras", "3s": "sucediera", "1p": "sucediéramos", "2p": "sucedierais", "3p": "sucedieran"}, "sufrir": {"1s": "sufriera", "2s": "sufrieras", "3s": "sufriera", "1p": "sufriéramos", "2p": "sufrierais", "3p": "sufrieran"}, "sugerir": {"1s": "sugiriera", "2s": "sugirieras", "3s": "sugiriera", "1p": "sugiriéramos", "2p": "sugirierais", "3p": "sugirieran"}, "suponer": {"1s": "supusiera", "2s": "supusieras", "3s": "supusiera", "1p": "supusiéramos", "2p": "supusierais", "3p": "supusieran"}, "surgir": {"1s": "surgiera", "2s": "surgieras", "3s": "surgiera", "1p": "surgiéramos", "2p": "surgierais", "3p": "surgieran"}, "suspirar": {"1s": "suspirara", "2s": "suspiraras", "3s": "suspirara", "1p": "suspiráramos", "2p": "suspirarais", "3p": "suspiraran"}, "sustituir": {"1s": "sustituyera", "2s": "sustituyeras", "3s": "sustituyera", "1p": "sustituyéramos", "2p": "sustituyerais", "3p": "sustituyeran"}, "tañer": {"1s": "tañera", "2s": "tañeras", "3s": "tañera", "1p": "tañéramos", "2p": "tañerais", "3p": "tañeran"}, "tapar": {"1s": "tapara", "2s": "taparas", "3s": "tapara", "1p": "tapáramos", "2p": "taparais", "3p": "taparan"}, "tardar": {"1s": "tardara", "2s": "tardaras", "3s": "tardara", "1p": "tardáramos", "2p": "tardarais", "3p": "tardaran"}, "temer": {"1s": "temiera", "2s": "temieras", "3s": "temiera", "1p": "temiéramos", "2p": "temierais", "3p": "temieran"}, "tener": {"1s": "tuviera", "2s": "tuvieras", "3s": "tuviera", "1p": "tuviéramos", "2p": "tuvierais", "3p": "tuvieran"}, "teñir": {"1s": "tiñera", "2s": "tiñeras", "3s": "tiñera", "1p": "tiñéramos", "2p": "tiñerais", "3p": "tiñeran"}, "terminar": {"1s": "terminara", "2s": "terminaras", "3s": "terminara", "1p": "termináramos", "2p": "terminarais", "3p": "terminaran"}, "tirar": {"1s": "tirara", "2s": "tiraras", "3s": "tirara", "1p": "tiráramos", "2p": "tirarais", "3p": "tiraran"}, "tocar": {"1s": "tocara", "2s": "tocaras", "3s": "tocara", "1p": "tocáramos", "2p": "tocarais", "3p": "tocaran"}, "tomar": {"1s": "tomara", "2s": "tomaras", "3s": "tomara", "1p": "tomáramos", "2p": "tomarais", "3p": "tomaran"}, "torcer": {"1s": "torciera", "2s": "torcieras", "3s": "torciera", "1p": "torciéramos", "2p": "torcierais", "3p": "torcieran"}, "toser": {"1s": "tosiera", "2s": "tosieras", "3s": "tosiera", "1p": "tosiéramos", "2p": "tosierais", "3p": "tosieran"}, "trabajar": {"1s": "trabajara", "2s": "trabajaras", "3s": "trabajara", "1p": "trabajáramos", "2p": "trabajarais", "3p": "trabajaran"}, "traducir": {"1s": "tradujera", "2s": "tradujeras", "3s": "tradujera", "1p": "tradujéramos", "2p": "tradujerais", "3p": "tradujeran"}, "traer": {"1s": "trajera", "2s": "trajeras", "3s": "trajera", "1p": "trajéramos", "2p": "trajerais", "3p": "trajeran"}, "tragar": {"1s": "tragara", "2s": "tragaras", "3s": "tragara", "1p": "tragáramos", "2p": "tragarais", "3p": "tragaran"}, "tratar": {"1s": "tratara", "2s": "trataras", "3s": "tratara", "1p": "tratáramos", "2p": "tratarais", "3p": "trataran"}, "triunfar": {"1s": "triunfara", "2s": "triunfaras", "3s": "triunfara", "1p": "triunfáramos", "2p": "triunfarais", "3p": "triunfaran"}, "tropezar": {"1s": "tropezara", "2s": "tropezaras", "3s": "tropezara", "1p": "tropezáramos", "2p": "tropezarais", "3p": "tropezaran"}, "ubicar": {"1s": "ubicara", "2s": "ubicaras", "3s": "ubicara", "1p": "ubicáramos", "2p": "ubicarais", "3p": "ubicaran"}, "unir": {"1s": "uniera", "2s": "unieras", "3s": "uniera", "1p": "uniéramos", "2p": "unierais", "3p": "unieran"}, "untar": {"1s": "untara", "2s": "untaras", "3s": "untara", "1p": "untáramos", "2p": "untarais", "3p": "untaran"}, "usar": {"1s": "usara", "2s": "usaras", "3s": "usara", "1p": "usáramos", "2p": "usarais", "3p": "usaran"}, "utilizar": {"1s": "utilizara", "2s": "utilizaras", "3s": "utilizara", "1p": "utilizáramos", "2p": "utilizarais", "3p": "utilizaran"}, "vaciar": {"1s": "vaciara", "2s": "vaciaras", "3s": "vaciara", "1p": "vaciáramos", "2p": "vaciarais", "3p": "vaciaran"}, "valer": {"1s": "valiera", "2s": "valieras", "3s": "valiera", "1p": "valiéramos", "2p": "valierais", "3p": "valieran"}, "variar": {"1s": "variara", "2s": "variaras", "3s": "variara", "1p": "variáramos", "2p": "variarais", "3p": "variaran"}, "vencer": {"1s": "venciera", "2s": "vencieras", "3s": "venciera", "1p": "venciéramos", "2p": "vencierais", "3p": "vencieran"}, "vender": {"1s": "vendiera", "2s": "vendieras", "3s": "vendiera", "1p": "vendiéramos", "2p": "vendierais", "3p": "vendieran"}, "venir": {"1s": "viniera", "2s": "vinieras", "3s": "viniera", "1p": "viniéramos", "2p": "vinierais", "3p": "vinieran"}, "ver": {"1s": "viera", "2s": "vieras", "3s": "viera", "1p": "viéramos", "2p": "vierais", "3p": "vieran"}, "verificar": {"1s": "verificara", "2s": "verificaras", "3s": "verificara", "1p": "verificáramos", "2p": "verificarais", "3p": "verificaran"}, "vestir": {"1s": "vistiera", "2s": "vistieras", "3s": "vistiera", "1p": "vistiéramos", "2p": "vistierais", "3p": "vistieran"}, "vestirse": {"1s": "me vistiera", "2s": "te vistieras", "3s": "se vistiera", "1p": "nos vistiéramos", "2p": "os vistierais", "3p": "se vistieran"}, "viajar": {"1s": "viajara", "2s": "viajaras", "3s": "viajara", "1p": "viajáramos", "2p": "viajarais", "3p": "viajaran"}, "violar": {"1s": "violara", "2s": "violaras", "3s": "violara", "1p": "violáramos", "2p": "violarais", "3p": "violaran"}, "visitar": {"1s": "visitara", "2s": "visitaras", "3s": "visitara", "1p": "visitáramos", "2p": "visitarais", "3p": "visitaran"}, "vivir": {"1s": "viviera", "2s": "vivieras", "3s": "viviera", "1p": "viviéramos", "2p": "vivierais", "3p": "vivieran"}, "volar": {"1s": "volara", "2s": "volaras", "3s": "volara", "1p": "voláramos", "2p": "volarais", "3p": "volaran"}, "volver": {"1s": "volviera", "2s": "volvieras", "3s": "volviera", "1p": "volviéramos", "2p": "volvierais", "3p": "volvieran"}, "vomitar": {"1s": "vomitara", "2s": "vomitaras", "3s": "vomitara", "1p": "vomitáramos", "2p": "vomitarais", "3p": "vomitaran"}, "votar": {"1s": "votara", "2s": "votaras", "3s": "votara", "1p": "votáramos", "2p": "votarais", "3p": "votaran"}, "yacer": {"1s": "yaciera", "2s": "yacieras", "3s": "yaciera", "1p": "yaciéramos", "2p": "yacierais", "3p": "yacieran"}, "zambullirse": {"1s": "me zambullera", "2s": "te zambulleras", "3s": "se zambullera", "1p": "nos zambulléramos", "2p": "os zambullerais", "3p": "se zambulleran"}, "besar": {"1s": "besara", "2s": "besaras", "3s": "besara", "1p": "besáramos", "2p": "besarais", "3p": "besaran"}, "bailar": {"1s": "bailara", "2s": "bailaras", "3s": "bailara", "1p": "bailáramos", "2p": "bailarais", "3p": "bailaran"}, "presentar": {"1s": "presentara", "2s": "presentaras", "3s": "presentara", "1p": "presentáramos", "2p": "presentarais", "3p": "presentaran"}, "esperar": {"1s": "esperara", "2s": "esperaras", "3s": "esperara", "1p": "esperáramos", "2p": "esperarais", "3p": "esperaran"}}